Workbook
Name EmployeeNames: 'Employee Records'!$A$2:$A$2047
Name EmployeePickList5: 'Employee Dropdown Lists'!$A$2:$A$201
Name EmployeePickList6: 'Employee Dropdown Lists'!$B$2:$B$201
Name EmployeePickList7: 'Employee Dropdown Lists'!$C$2:$C$201
Name EmployeePickList8: 'Employee Dropdown Lists'!$D$2:$D$201
Name EmployeePickList9: 'Employee Dropdown Lists'!$E$2:$E$201
Name EmployeePickList10: 'Employee Dropdown Lists'!$F$2:$F$201
Name EmployeePickList11: 'Employee Dropdown Lists'!$G$2:$G$201
Name EmployeePickList12: 'Employee Dropdown Lists'!$H$2:$H$201
Name EmployeePickList13: 'Employee Dropdown Lists'!$I$2:$I$201
Name EmployeePickList14: 'Employee Dropdown Lists'!$J$2:$J$201
Name EmployeePickList15: 'Employee Dropdown Lists'!$K$2:$K$201
Name EmployeePickList16: 'Employee Dropdown Lists'!$L$2:$L$201
Name EmployeePickList17: 'Employee Dropdown Lists'!$M$2:$M$201
Name EmployeePickList18: 'Employee Dropdown Lists'!$N$2:$N$201
Name EmployeePickList19: 'Employee Dropdown Lists'!$O$2:$O$201
Name EmployeePickList20: 'Employee Dropdown Lists'!$P$2:$P$201
Name EmployeePickList21: 'Employee Dropdown Lists'!$Q$2:$Q$201
Name EmployeePickList22: 'Employee Dropdown Lists'!$R$2:$R$201
Name EmployeePickList23: 'Employee Dropdown Lists'!$S$2:$S$201
Name EmployeePickList24: 'Employee Dropdown Lists'!$T$2:$T$201
Name EmployeePickList25: 'Employee Dropdown Lists'!$U$2:$U$201
Name EmployeePickList26: 'Employee Dropdown Lists'!$V$2:$V$201
Name EmployeePickList27: 'Employee Dropdown Lists'!$W$2:$W$201
Name EmployeePickList28: 'Employee Dropdown Lists'!$X$2:$X$201
Name EmployeePickList29: 'Employee Dropdown Lists'!$Y$2:$Y$201
Name EmployeePickList30: 'Employee Dropdown Lists'!$Z$2:$Z$201
Name EmployeePickList31: 'Employee Dropdown Lists'!$AA$2:$AA$201
Name EmployeePickList32: 'Employee Dropdown Lists'!$AB$2:$AB$201
Name EmployeePickList33: 'Employee Dropdown Lists'!$AC$2:$AC$201
Name EmployeePickList34: 'Employee Dropdown Lists'!$AD$2:$AD$201
Name EmployeePickList35: 'Employee Dropdown Lists'!$AE$2:$AE$201
Name EmployeePickList36: 'Employee Dropdown Lists'!$AF$2:$AF$201
Name EmployeePickList37: 'Employee Dropdown Lists'!$AG$2:$AG$201
Name EmployeePickList38: 'Employee Dropdown Lists'!$AH$2:$AH$201
Name EmployeePickList39: 'Employee Dropdown Lists'!$AI$2:$AI$201
Name EmployeePickList40: 'Employee Dropdown Lists'!$AJ$2:$AJ$201
Name EmployeePickList41: 'Employee Dropdown Lists'!$AK$2:$AK$201
Name EmployeePickList42: 'Employee Dropdown Lists'!$AL$2:$AL$201
Name EmployeePickList43: 'Employee Dropdown Lists'!$AM$2:$AM$201
Name EmployeePickList44: 'Employee Dropdown Lists'!$AN$2:$AN$201
Name EmployeePickList45: 'Employee Dropdown Lists'!$AO$2:$AO$201
Name EmployeePickList46: 'Employee Dropdown Lists'!$AP$2:$AP$201
Name EmployeePickList47: 'Employee Dropdown Lists'!$AQ$2:$AQ$201
Name EmployeePickList48: 'Employee Dropdown Lists'!$AR$2:$AR$201
Name EmployeePickList49: 'Employee Dropdown Lists'!$AS$2:$AS$201
Name EmployeePickList50: 'Employee Dropdown Lists'!$AT$2:$AT$201
Name EmployeePickList51: 'Employee Dropdown Lists'!$AU$2:$AU$201
Name EmployeePickList52: 'Employee Dropdown Lists'!$AV$2:$AV$201
Name EmployeePickList53: 'Employee Dropdown Lists'!$AW$2:$AW$201
Name EmployeePickList54: 'Employee Dropdown Lists'!$AX$2:$AX$201
Name EmployeePickList55: 'Employee Dropdown Lists'!$AY$2:$AY$201
Name EmployeePickList56: 'Employee Dropdown Lists'!$AZ$2:$AZ$201
Name EmployeePickList57: 'Employee Dropdown Lists'!$BA$2:$BA$201
Name EmployeePickList58: 'Employee Dropdown Lists'!$BB$2:$BB$201
Name EmployeePickList59: 'Employee Dropdown Lists'!$BC$2:$BC$201
Name EmployeePickList60: 'Employee Dropdown Lists'!$BD$2:$BD$201
Name EmployeePickList61: 'Employee Dropdown Lists'!$BE$2:$BE$201
Name EmployeePickList62: 'Employee Dropdown Lists'!$BF$2:$BF$201
Name EmployeePickList63: 'Employee Dropdown Lists'!$BG$2:$BG$201

Sheet Loan Due Import
A1: Entity | B1: GSIS | C1: Use one entity for the whole file.
A4: Due Month | B4: Employee Search | C4: Employee ID | D4: Employee Name | E4: Loan/Account No. | F4: Loan Type | G4: Monthly Amortization | H4: Amount Due | I4: Outstanding Balance | J4: Principal Due | K4: Interest Due | L4: Penalty Due | M4: Remarks
A5: 2026-05-01 | B5: ACOSTA | C5: =IFERROR(VLOOKUP(D5,'Employee Records'!$A$2:$B$2047,2,FALSE),"") -> 002129 | D5: ACOSTA, JESSIE JAMES CALUYA | E5: TEST-002129-0001 | F5: Salary Loan | G5: 1250 | H5: 1275 | I5: 25000 | J5: 1025 | K5: 200 | L5: 50 | M5: Sample IHOMP test row
A6: 2026-05-01 | B6: ACOSTA | C6: =IFERROR(VLOOKUP(D6,'Employee Records'!$A$2:$B$2047,2,FALSE),"") -> 001808 | D6: ACOSTA, JONATHAN CALUYA | E6: TEST-001808-0002 | F6: MPL | G6: 1625.25 | H6: 1592.75 | I6: 29250 | J6: 1332.71 | K6: 260.04 | L6: 0 | M6: Sample IHOMP test row
A7: 2026-05-01 | B7: AGBAYANI | C7: =IFERROR(VLOOKUP(D7,'Employee Records'!$A$2:$B$2047,2,FALSE),"") -> 002515 | D7: AGBAYANI, MARK LAURENCE DOROYAN | E7: TEST-002515-0003 | F7: Emergency Loan | G7: 2000.5 | H7: 1960.49 | I7: 33500 | J7: 1640.41 | K7: 320.08 | L7: 0 | M7: Sample IHOMP test row
A8: 2026-05-01 | B8: AGTANG | C8: =IFERROR(VLOOKUP(D8,'Employee Records'!$A$2:$B$2047,2,FALSE),"") -> 002745 | D8: AGTANG, RHONA MHEA JOY ASUNCION | E8: TEST-002745-0004 | F8: Livelihood Loan | G8: 2375.75 | H8: 2328.24 | I8: 37750 | J8: 1948.12 | K8: 380.12 | L8: 0 | M8: Sample IHOMP test row
A9: 2026-05-01 | B9: AGULAY | C9: =IFERROR(VLOOKUP(D9,'Employee Records'!$A$2:$B$2047,2,FALSE),"") -> 000539 | D9: AGULAY, DENNIS MANGLAL-LAN | E9: TEST-000539-0005 | F9: Calamity Loan | G9: 2751 | H9: 2745.98 | I9: 42000 | J9: 2255.82 | K9: 440.16 | L9: 50 | M9: Sample IHOMP test row
A10: 2026-05-01 | B10: ANDRES | C10: =IFERROR(VLOOKUP(D10,'Employee Records'!$A$2:$B$2047,2,FALSE),"") -> 002966 | D10: ANDRES, STEPHEN JOHN DIVINA | E10: TEST-002966-0006 | F10: Policy Loan | G10: 3126.25 | H10: 3063.73 | I10: 46250 | J10: 2563.53 | K10: 500.2 | L10: 0 | M10: Sample IHOMP test row
A11: 2026-05-01 | B11: CALACAL | C11: =IFERROR(VLOOKUP(D11,'Employee Records'!$A$2:$B$2047,2,FALSE),"") -> 002870 | D11: CALACAL, CARLA NIÑA SADORRA | E11: TEST-002870-0007 | F11: Salary Loan | G11: 3501.5 | H11: 3431.47 | I11: 50500 | J11: 2871.23 | K11: 560.24 | L11: 0 | M11: Sample IHOMP test row
A12: 2026-05-01 | B12: DANCEL | C12: =IFERROR(VLOOKUP(D12,'Employee Records'!$A$2:$B$2047,2,FALSE),"") -> 001165 | D12: DANCEL, CHRISTIAN JAMES BUENO | E12: TEST-001165-0008 | F12: MPL | G12: 3876.75 | H12: 3799.22 | I12: 54750 | J12: 3178.94 | K12: 620.28 | L12: 0 | M12: Sample IHOMP test row
A13: 2026-05-01 | B13: DARIA | C13: =IFERROR(VLOOKUP(D13,'Employee Records'!$A$2:$B$2047,2,FALSE),"") -> 001527 | D13: DARIA, ALDRIN DUMLAO | E13: TEST-001527-0009 | F13: Emergency Loan | G13: 4252 | H13: 4216.96 | I13: 59000 | J13: 3486.64 | K13: 680.32 | L13: 50 | M13: Sample IHOMP test row
A14: 2026-05-01 | B14: DUQUE | C14: =IFERROR(VLOOKUP(D14,'Employee Records'!$A$2:$B$2047,2,FALSE),"") -> 002751 | D14: DUQUE, DAYZELLE MOLINES | E14: TEST-002751-0010 | F14: Livelihood Loan | G14: 4627.25 | H14: 4534.71 | I14: 63250 | J14: 3794.35 | K14: 740.36 | L14: 0 | M14: Sample IHOMP test row
A15: 2026-05-01 | B15: EDNILAO | C15: =IFERROR(VLOOKUP(D15,'Employee Records'!$A$2:$B$2047,2,FALSE),"") -> 002170 | D15: EDNILAO, CHRISTIAN PAUL FUERTES | E15: TEST-002170-0011 | F15: Calamity Loan | G15: 5002.5 | H15: 4902.45 | I15: 67500 | J15: 4102.05 | K15: 800.4 | L15: 0 | M15: Sample IHOMP test row
A16: 2026-05-01 | B16: FORMOSO | C16: =IFERROR(VLOOKUP(D16,'Employee Records'!$A$2:$B$2047,2,FALSE),"") -> 001030 | D16: FORMOSO, RAY VINCENT FLORES | E16: TEST-001030-0012 | F16: Policy Loan | G16: 5377.75 | H16: 5270.2 | I16: 71750 | J16: 4409.76 | K16: 860.44 | L16: 0 | M16: Sample IHOMP test row
C17: =IFERROR(VLOOKUP(D17,'Employee Records'!$A$2:$B$2047,2,FALSE),"")
C18: =IFERROR(VLOOKUP(D18,'Employee Records'!$A$2:$B$2047,2,FALSE),"")
C19: =IFERROR(VLOOKUP(D19,'Employee Records'!$A$2:$B$2047,2,FALSE),"")
C20: =IFERROR(VLOOKUP(D20,'Employee Records'!$A$2:$B$2047,2,FALSE),"")
C21: =IFERROR(VLOOKUP(D21,'Employee Records'!$A$2:$B$2047,2,FALSE),"")
C22: =IFERROR(VLOOKUP(D22,'Employee Records'!$A$2:$B$2047,2,FALSE),"")
C23: =IFERROR(VLOOKUP(D23,'Employee Records'!$A$2:$B$2047,2,FALSE),"")
C24: =IFERROR(VLOOKUP(D24,'Employee Records'!$A$2:$B$2047,2,FALSE),"")
C25: =IFERROR(VLOOKUP(D25,'Employee Records'!$A$2:$B$2047,2,FALSE),"")
C26: =IFERROR(VLOOKUP(D26,'Employee Records'!$A$2:$B$2047,2,FALSE),"")
C27: =IFERROR(VLOOKUP(D27,'Employee Records'!$A$2:$B$2047,2,FALSE),"")
C28: =IFERROR(VLOOKUP(D28,'Employee Records'!$A$2:$B$2047,2,FALSE),"")
... C504: =IFERROR(VLOOKUP(D504,'Employee Records'!$A$2:$B$2047,2,FALSE),"")

Sheet Employee Records
A1: Employee Name | B1: Employee ID | C1: Lastname | D1: Firstname | E1: Middlename
A2: ABAD, FLORIDA RAMOS | B2: 000001 | C2: ABAD | D2: FLORIDA | E2: RAMOS
A3: ABAINZA, SHEENA GRACE BUMAGAT | B3: 001533 | C3: ABAINZA | D3: SHEENA GRACE | E3: BUMAGAT
A4: ABANSI, JELYNNE PISTOLA | B4: 002033 | C4: ABANSI | D4: JELYNNE | E4: PISTOLA
A5: ABARA, REGINA JASMINE RAMOS | B5: 000983 | C5: ABARA | D5: REGINA JASMINE | E5: RAMOS
A6: ABELLA, ADRIENNE RICA BUTAC | B6: 002738 | C6: ABELLA | D6: ADRIENNE RICA | E6: BUTAC
A7: ABELLA, LOVELY JOY BALGUNA | B7: 001648 | C7: ABELLA | D7: LOVELY JOY | E7: BALGUNA
A8: ABELLON, EVIE MAE ACOBA | B8: 001359 | C8: ABELLON | D8: EVIE MAE | E8: ACOBA
A9: ABELLON, GREGG JOHANESS SOLSOLOY | B9: 001103 | C9: ABELLON | D9: GREGG JOHANESS | E9: SOLSOLOY
A10: ABELLON, JAYSON MC ANGELO GALACGAC | B10: 000589 | C10: ABELLON | D10: JAYSON MC ANGELO | E10: GALACGAC
A11: ABELLON, LEO ANGELO GAPUZAN | B11: 002916 | C11: ABELLON | D11: LEO ANGELO | E11: GAPUZAN
A12: ABENES, JESS EMMANUEL VALDEZ | B12: 002613 | C12: ABENES | D12: JESS EMMANUEL | E12: VALDEZ
... A31: ACIERTO, CARLO BANES | B31: 000007 | C31: ACIERTO | D31: CARLO | E31: BANES
A32: ACIO, JENNA MEI AGULLANA | B32: 100001 | C32: ACIO | D32: JENNA MEI | E32: AGULLANA
A33: ACOB, CLARK - ANTHONY BACLIG | B33: 002416 | C33: ACOB | D33: CLARK - ANTHONY | E33: BACLIG
A34: ACOBA, MANUEL CHRISTIENSEN JUSTINE CASTRO | B34: 002929 | C34: ACOBA | D34: MANUEL CHRISTIENSEN JUSTINE | E34: CASTRO
A35: ACOSTA, ANNE GELLE BRIDGITTE GABUTEN | B35: 002233 | C35: ACOSTA | D35: ANNE GELLE BRIDGITTE | E35: GABUTEN
A36: ACOSTA, GENEVE ANDRES | B36: 001865 | C36: ACOSTA | D36: GENEVE | E36: ANDRES
A37: ACOSTA, JAYSON DOMINGO | B37: 002232 | C37: ACOSTA | D37: JAYSON | E37: DOMINGO
A38: ACOSTA, JEMY ARMYN BLANZA | B38: 002500 | C38: ACOSTA | D38: JEMY ARMYN | E38: BLANZA
A39: ACOSTA, JERICO ALLAN CALUYA | B39: 000590 | C39: ACOSTA | D39: JERICO ALLAN | E39: CALUYA
A40: ACOSTA, JESSIE JAMES CALUYA | B40: 002129 | C40: ACOSTA | D40: JESSIE JAMES | E40: CALUYA
A41: ACOSTA, JONATHAN CALUYA | B41: 001808 | C41: ACOSTA | D41: JONATHAN | E41: CALUYA
A42: ACOSTA, MA. ANGELICA TORIBIO | B42: 002953 | C42: ACOSTA | D42: MA. ANGELICA | E42: TORIBIO
A43: ACUÑA, GRACHELE CHARM ASUNCION | B43: 002704 | C43: ACUÑA | D43: GRACHELE CHARM | E43: ASUNCION
A44: ADALLA, LYLA EDISSEY FLOJO | B44: 001079 | C44: ADALLA | D44: LYLA EDISSEY | E44: FLOJO
... A46: ADAME, NIÑA MARIE PANGANIBAN | B46: 002479 | C46: ADAME | D46: NIÑA MARIE | E46: PANGANIBAN
A47: ADOLFO, JOSHUA | B47: 002830 | C47: ADOLFO | D47: JOSHUA
A48: ADVINCULA, MARY ANTONETTE RAÑA | B48: 001532 | C48: ADVINCULA | D48: MARY ANTONETTE | E48: RAÑA
A49: AFROILAN, REGIENALD ACAIN | B49: 002160 | C49: AFROILAN | D49: REGIENALD | E49: ACAIN
A50: AGABIN, JANE CHRISTINE VERGARA | B50: 001509 | C50: AGABIN | D50: JANE CHRISTINE | E50: VERGARA
A51: AGACIA, JEANIN REMEBEL PEDROLA | B51: GIP-061 | C51: AGACIA | D51: JEANIN REMEBEL | E51: PEDROLA
A52: AGACIA, RACHELLE MAE COLOMA | B52: 001272 | C52: AGACIA | D52: RACHELLE MAE | E52: COLOMA
A53: AGANUS, KRISTINE JOY MATABANG | B53: 001185 | C53: AGANUS | D53: KRISTINE JOY | E53: MATABANG
A54: AGARPAO, ESPERANZA GUILLERMO | B54: 000104 | C54: AGARPAO | D54: ESPERANZA | E54: GUILLERMO
A55: AGARPAO, SHELLA MAY BALBAG | B55: 001588 | C55: AGARPAO | D55: SHELLA MAY | E55: BALBAG
A56: AGAS, MHEL ANTHONY | B56: 002971 | C56: AGAS | D56: MHEL ANTHONY
A57: AGBANNAOAG, JULIMAR MORALES | B57: 001628 | C57: AGBANNAOAG | D57: JULIMAR | E57: MORALES
A58: AGBAYANI, ELYKA LAURECE DOROYAN | B58: 002952 | C58: AGBAYANI | D58: ELYKA LAURECE | E58: DOROYAN
A59: AGBAYANI, MARK LAURENCE DOROYAN | B59: 002515 | C59: AGBAYANI | D59: MARK LAURENCE | E59: DOROYAN
A60: AGCAOILI, ANNAH MIKAELA LAGMAY | B60: 002508 | C60: AGCAOILI | D60: ANNAH MIKAELA | E60: LAGMAY
A61: AGCAOILI, ESTRELITA ESTOESTA | B61: 002109 | C61: AGCAOILI | D61: ESTRELITA | E61: ESTOESTA
A62: AGCAOILI, WIHL JAY CAMANGEG | B62: 001211 | C62: AGCAOILI | D62: WIHL JAY | E62: CAMANGEG
A63: AGDEPPA, JESSA MAY ALEGADO | B63: 000869 | C63: AGDEPPA | D63: JESSA MAY | E63: ALEGADO
A64: AGDIGOS, BRIAN CHRISTIAN GONGORA | B64: 000011 | C64: AGDIGOS | D64: BRIAN CHRISTIAN | E64: GONGORA
A65: AGDIGOS, DHONNA MAE GAOAT | B65: 001672 | C65: AGDIGOS | D65: DHONNA MAE | E65: GAOAT
A66: AGLIAM, ALEXANDER CHRISTIAN BILANGO | B66: 001626 | C66: AGLIAM | D66: ALEXANDER CHRISTIAN | E66: BILANGO
A67: AGLIAM, MARX CHESTER ELECANAL | B67: 001888 | C67: AGLIAM | D67: MARX CHESTER | E67: ELECANAL
A68: AGLIPAY, CHRISTIAN PAUL MAMOTOS | B68: 001977 | C68: AGLIPAY | D68: CHRISTIAN PAUL | E68: MAMOTOS
... A73: AGRAAN, CHRISTIAN AMBER AGUSTIN | B73: 000785 | C73: AGRAAN | D73: CHRISTIAN AMBER | E73: AGUSTIN
A74: AGRES, LEVY JAYNE BAYANGOS | B74: 100006 | C74: AGRES | D74: LEVY JAYNE | E74: BAYANGOS
A75: AGTANG, RHONA MHEA JOY ASUNCION | B75: 002745 | C75: AGTANG | D75: RHONA MHEA JOY | E75: ASUNCION
A76: AGTINA, CHARLIE ORTAL | B76: 001798 | C76: AGTINA | D76: CHARLIE | E76: ORTAL
A77: AGUADA, LLANEL KRISTEN ACERET | B77: 002333 | C77: AGUADA | D77: LLANEL KRISTEN | E77: ACERET
A78: AGUADA, LOUELLA ACERET | B78: 002382 | C78: AGUADA | D78: LOUELLA | E78: ACERET
A79: AGUDONG, RAYMARK GANITANO | B79: 001005 | C79: AGUDONG | D79: RAYMARK | E79: GANITANO
A80: AGUIBITIN, FREDIE LEGASPI | B80: 000298 | C80: AGUIBITIN | D80: FREDIE | E80: LEGASPI
A81: AGUIBITIN, PETER CABANADO | B81: 002924 | C81: AGUIBITIN | D81: PETER | E81: CABANADO
A82: AGUILAR, EPHRAIN LAGUA | B82: 001303 | C82: AGUILAR | D82: EPHRAIN | E82: LAGUA
A83: AGUILAR, MANILYN TAMBUA | B83: 001908 | C83: AGUILAR | D83: MANILYN | E83: TAMBUA
A84: AGUILAR, MARICON CAOILI | B84: 002192 | C84: AGUILAR | D84: MARICON | E84: CAOILI
A85: AGUILAR, RENNEIGH RARANGOL | B85: 002995 | C85: AGUILAR | D85: RENNEIGH | E85: RARANGOL
A86: AGUILLON, ABIGAEL AGUEDAN | B86: 002483 | C86: AGUILLON | D86: ABIGAEL | E86: AGUEDAN
... A268: BAGA, ELMAR JOHN MALOOM | B268: 002858 | C268: BAGA | D268: ELMAR JOHN | E268: MALOOM
A269: BAGA, GIANNA RONA BEATRIZ DIGAP | B269: 100059 | C269: BAGA | D269: GIANNA RONA BEATRIZ | E269: DIGAP
A270: BAGAOISAN, ANGELICA CABANILLA | B270: 001317 | C270: BAGAOISAN | D270: ANGELICA | E270: CABANILLA
A271: BAGAOISAN, DAVID JOHN COLOMA | B271: 002175 | C271: BAGAOISAN | D271: DAVID JOHN | E271: COLOMA
A272: BAGAOISAN, DONNALYN PAHINAG | B272: 002337 | C272: BAGAOISAN | D272: DONNALYN | E272: PAHINAG
A273: BAGAOISAN, JULIET GALAD | B273: 002987 | C273: BAGAOISAN | D273: JULIET | E273: GALAD
A274: BAGAOISAN, MARC CHRISTIAN COLOMA | B274: 000543 | C274: BAGAOISAN | D274: MARC CHRISTIAN | E274: COLOMA
A275: BAGAOISAN, VIC PAUL AGUSTIN | B275: 001325 | C275: BAGAOISAN | D275: VIC PAUL | E275: AGUSTIN
A276: BAGARRA, GLENN ELOVINO | B276: 000488 | C276: BAGARRA | D276: GLENN | E276: ELOVINO
A277: BAGASIN, NESTER JAMES SALLUTAL | B277: 001965 | C277: BAGASIN | D277: NESTER JAMES | E277: SALLUTAL
A278: BAGASIN, TERRY ANNE SALLUTAL | B278: 002763 | C278: BAGASIN | D278: TERRY ANNE | E278: SALLUTAL
A279: BAGASOL, PATRICK JOHN VISITACION | B279: 001263 | C279: BAGASOL | D279: PATRICK JOHN | E279: VISITACION
A280: BAGAY, MA. KRISTELA LOU BATALLA | B280: 002866 | C280: BAGAY | D280: MA. KRISTELA LOU | E280: BATALLA
A281: BAGAY, MARVIN ROSGUETA | B281: 000911 | C281: BAGAY | D281: MARVIN | E281: ROSGUETA
... A291: BALAN, ANTHONY MARIANO | B291: 002749 | C291: BALAN | D291: ANTHONY | E291: MARIANO
A292: BALANI, NICKSON | B292: EXT-0008 | C292: BALANI | D292: NICKSON
A293: BALAQUI, SHERYL ANNE MARIANO | B293: 001451 | C293: BALAQUI | D293: SHERYL ANNE | E293: MARIANO
A294: BALBAG, DANILO ROSCAL | B294: 001573 | C294: BALBAG | D294: DANILO | E294: ROSCAL
A295: BALBUENA, JENNIFER YACAPIN | B295: 001867 | C295: BALBUENA | D295: JENNIFER | E295: YACAPIN
A296: BALDOS, JASMINE HAZEL CORPUZ | B296: INTERN-0006 | C296: BALDOS | D296: JASMINE HAZEL | E296: CORPUZ
A297: BALGUNA, CHRISTIAN ZEN . | B297: 001097 | C297: BALGUNA | D297: CHRISTIAN ZEN | E297: .
A298: BALICAT, ABIGAIL GARVIDA | B298: 000861 | C298: BALICAT | D298: ABIGAIL | E298: GARVIDA
A299: BALIDOC, CHERIE CLAIRE MARTIN | B299: 002304 | C299: BALIDOC | D299: CHERIE CLAIRE | E299: MARTIN
A300: BALIGAT, LEONEL MANGLAL-LAN | B300: 000316 | C300: BALIGAT | D300: LEONEL | E300: MANGLAL-LAN
A301: BALIGOD, CHRISTOPHER TELAN | B301: 002410 | C301: BALIGOD | D301: CHRISTOPHER | E301: TELAN
A302: BALIGOD, LOVIE JANE MADRIAGA | B302: 001894 | C302: BALIGOD | D302: LOVIE JANE | E302: MADRIAGA
A303: BALINTONA, JAYMAR BUMANGLAG | B303: 001851 | C303: BALINTONA | D303: JAYMAR | E303: BUMANGLAG
A304: BALISACAN, JELYN LLANES | B304: 001513 | C304: BALISACAN | D304: JELYN | E304: LLANES
... A345: BATARA, JEIZEL AIRA RAMOS | B345: 001184 | C345: BATARA | D345: JEIZEL AIRA | E345: RAMOS
A346: BATARA, MARY JOY | B346: 001614 | C346: BATARA | D346: MARY JOY
A347: BATOON, GENEVIEVE SAGADRACA | B347: 000412 | C347: BATOON | D347: GENEVIEVE | E347: SAGADRACA
A348: BATOON, KAREN BONIFACIO | B348: 002892 | C348: BATOON | D348: KAREN | E348: BONIFACIO
A349: BATTAD, MARVIN PALAFOX | B349: 000796 | C349: BATTAD | D349: MARVIN | E349: PALAFOX
A350: BATTULAYAN, ALEXANDRIA JAMAE AGUDELO | B350: 002843 | C350: BATTULAYAN | D350: ALEXANDRIA JAMAE | E350: AGUDELO
A351: BATTULAYAN, ARLENE AGUDELO | B351: 000032 | C351: BATTULAYAN | D351: ARLENE | E351: AGUDELO
A352: BATTULAYAN, ROLANDO LONGBOY | B352: 001604 | C352: BATTULAYAN | D352: ROLANDO | E352: LONGBOY
A353: BATTULAYAN, ROMEO MAPALA | B353: 001455 | C353: BATTULAYAN | D353: ROMEO | E353: MAPALA
...

Sheet Employee Dropdown Lists
A1: Row 5 | B1: Row 6 | C1: Row 7 | D1: Row 8 | E1: Row 9 | F1: Row 10 | G1: Row 11 | H1: Row 12 | I1: Row 13 | J1: Row 14 | K1: Row 15 | L1: Row 16 | M1: Row 17 | N1: Row 18 | O1: Row 19 | P1: Row 20 | Q1: Row 21 | R1: Row 22 | S1: Row 23 | T1: Row 24 | U1: Row 25 | V1: Row 26 | W1: Row 27 | X1: Row 28 | Y1: Row 29 | Z1: Row 30 | AA1: Row 31 | AB1: Row 32 | AC1: Row 33 | AD1: Row 34 | AE1: Row 35 | AF1: Row 36 | AG1: Row 37 | AH1: Row 38 | AI1: Row 39 | AJ1: Row 40 | AK1: Row 41 | AL1: Row 42 | AM1: Row 43 | AN1: Row 44 | AO1: Row 45 | AP1: Row 46 | AQ1: Row 47 | AR1: Row 48 | AS1: Row 49 | AT1: Row 50 | AU1: Row 51 | AV1: Row 52 | AW1: Row 53 | AX1: Row 54 | AY1: Row 55 | AZ1: Row 56 | BA1: Row 57 | BB1: Row 58 | BC1: Row 59 | BD1: Row 60 | BE1: Row 61 | BF1: Row 62 | BG1: Row 63 | BH1: Row 64 | BI1: Row 65 | BJ1: Row 66 | BK1: Row 67 | BL1: Row 68 | BM1: Row 69 | BN1: Row 70 | BO1: Row 71 | BP1: Row 72 | BQ1: Row 73 | BR1: Row 74 | BS1: Row 75 | BT1: Row 76 | BU1: Row 77 | BV1: Row 78 | BW1: Row 79 | BX1: Row 80 | BY1: Row 81 | BZ1: Row 82 | CA1: Row 83 | CB1: Row 84 | CC1: Row 85 | CD1: Row 86 | CE1: Row 87 | CF1: Row 88 | CG1: Row 89 | CH1: Row 90 | CI1: Row 91 | CJ1: Row 92 | CK1: Row 93 | CL1: Row 94 | CM1: Row 95 | CN1: Row 96 | CO1: Row 97 | CP1: Row 98 | CQ1: Row 99 | CR1: Row 100 | CS1: Row 101 | CT1: Row 102 | CU1: Row 103 | CV1: Row 104 | CW1: Row 105 | CX1: Row 106 | CY1: Row 107 | CZ1: Row 108 | DA1: Row 109 | DB1: Row 110 | DC1: Row 111 | DD1: Row 112 | DE1: Row 113 | DF1: Row 114 | DG1: Row 115 | DH1: Row 116 | DI1: Row 117 | DJ1: Row 118 | DK1: Row 119 | DL1: Row 120 | DM1: Row 121 | DN1: Row 122 | DO1: Row 123 | DP1: Row 124 | DQ1: Row 125 | DR1: Row 126 | DS1: Row 127 | DT1: Row 128 | DU1: Row 129 | DV1: Row 130 | DW1: Row 131 | DX1: Row 132 | DY1: Row 133 | DZ1: Row 134 | EA1: Row 135 | EB1: Row 136 | EC1: Row 137 | ED1: Row 138 | EE1: Row 139 | EF1: Row 140 | EG1: Row 141 | EH1: Row 142 | EI1: Row 143 | EJ1: Row 144 | EK1: Row 145 | EL1: Row 146 | EM1: Row 147 | EN1: Row 148 | EO1: Row 149 | EP1: Row 150 | EQ1: Row 151 | ER1: Row 152 | ES1: Row 153 | ET1: Row 154 | EU1: Row 155 | EV1: Row 156 | EW1: Row 157 | EX1: Row 158 | EY1: Row 159 | EZ1: Row 160 | FA1: Row 161 | FB1: Row 162 | FC1: Row 163 | FD1: Row 164 | FE1: Row 165 | FF1: Row 166 | FG1: Row 167 | FH1: Row 168 | FI1: Row 169 | FJ1: Row 170 | FK1: Row 171 | FL1: Row 172 | FM1: Row 173 | FN1: Row 174 | FO1: Row 175 | FP1: Row 176 | FQ1: Row 177 | FR1: Row 178 | FS1: Row 179 | FT1: Row 180 | FU1: Row 181 | FV1: Row 182 | FW1: Row 183 | FX1: Row 184 | FY1: Row 185 | FZ1: Row 186 | GA1: Row 187 | GB1: Row 188 | GC1: Row 189 | GD1: Row 190 | GE1: Row 191 | GF1: Row 192 | GG1: Row 193 | GH1: Row 194 | GI1: Row 195 | GJ1: Row 196 | GK1: Row 197 | GL1: Row 198 | GM1: Row 199 | GN1: Row 200 | GO1: Row 201 | GP1: Row 202 | GQ1: Row 203 | GR1: Row 204 | GS1: Row 205 | GT1: Row 206 | GU1: Row 207 | GV1: Row 208 | GW1: Row 209 | GX1: Row 210 | GY1: Row 211 | GZ1: Row 212 | HA1: Row 213 | HB1: Row 214 | HC1: Row 215 | HD1: Row 216 | HE1: Row 217 | HF1: Row 218 | HG1: Row 219 | HH1: Row 220 | HI1: Row 221 | HJ1: Row 222 | HK1: Row 223 | HL1: Row 224 | HM1: Row 225 | HN1: Row 226 | HO1: Row 227 | HP1: Row 228 | HQ1: Row 229 | HR1: Row 230 | HS1: Row 231 | HT1: Row 232 | HU1: Row 233 | HV1: Row 234 | HW1: Row 235 | HX1: Row 236 | HY1: Row 237 | HZ1: Row 238 | IA1: Row 239 | IB1: Row 240 | IC1: Row 241 | ID1: Row 242 | IE1: Row 243 | IF1: Row 244 | IG1: Row 245 | IH1: Row 246 | II1: Row 247 | IJ1: Row 248 | IK1: Row 249 | IL1: Row 250 | IM1: Row 251 | IN1: Row 252 | IO1: Row 253 | IP1: Row 254 | IQ1: Row 255 | IR1: Row 256 | IS1: Row 257 | IT1: Row 258 | IU1: Row 259 | IV1: Row 260 | IW1: Row 261 | IX1: Row 262 | IY1: Row 263 | IZ1: Row 264 | JA1: Row 265 | JB1: Row 266 | JC1: Row 267 | JD1: Row 268 | JE1: Row 269 | JF1: Row 270 | JG1: Row 271 | JH1: Row 272 | JI1: Row 273 | JJ1: Row 274 | JK1: Row 275 | JL1: Row 276 | JM1: Row 277 | JN1: Row 278 | JO1: Row 279 | JP1: Row 280 | JQ1: Row 281 | JR1: Row 282 | JS1: Row 283 | JT1: Row 284 | JU1: Row 285 | JV1: Row 286 | JW1: Row 287 | JX1: Row 288 | JY1: Row 289 | JZ1: Row 290 | KA1: Row 291 | KB1: Row 292 | KC1: Row 293 | KD1: Row 294 | KE1: Row 295 | KF1: Row 296 | KG1: Row 297 | KH1: Row 298 | KI1: Row 299 | KJ1: Row 300 | KK1: Row 301 | KL1: Row 302 | KM1: Row 303 | KN1: Row 304 | KO1: Row 305 | KP1: Row 306 | KQ1: Row 307 | KR1: Row 308 | KS1: Row 309 | KT1: Row 310 | KU1: Row 311 | KV1: Row 312 | KW1: Row 313 | KX1: Row 314 | KY1: Row 315 | KZ1: Row 316 | LA1: Row 317 | LB1: Row 318 | LC1: Row 319 | LD1: Row 320 | LE1: Row 321 | LF1: Row 322 | LG1: Row 323 | LH1: Row 324 | LI1: Row 325 | LJ1: Row 326 | LK1: Row 327 | LL1: Row 328 | LM1: Row 329 | LN1: Row 330 | LO1: Row 331 | LP1: Row 332 | LQ1: Row 333 | LR1: Row 334 | LS1: Row 335 | LT1: Row 336 | LU1: Row 337 | LV1: Row 338 | LW1: Row 339 | LX1: Row 340 | LY1: Row 341 | LZ1: Row 342 | MA1: Row 343 | MB1: Row 344 | MC1: Row 345 | MD1: Row 346 | ME1: Row 347 | MF1: Row 348 | MG1: Row 349 | MH1: Row 350 | MI1: Row 351 | MJ1: Row 352 | MK1: Row 353 | ML1: Row 354 | MM1: Row 355 | MN1: Row 356 | MO1: Row 357 | MP1: Row 358 | MQ1: Row 359 | MR1: Row 360 | MS1: Row 361 | MT1: Row 362 | MU1: Row 363 | MV1: Row 364 | MW1: Row 365 | MX1: Row 366 | MY1: Row 367 | MZ1: Row 368 | NA1: Row 369 | NB1: Row 370 | NC1: Row 371 | ND1: Row 372 | NE1: Row 373 | NF1: Row 374 | NG1: Row 375 | NH1: Row 376 | NI1: Row 377 | NJ1: Row 378 | NK1: Row 379 | NL1: Row 380 | NM1: Row 381 | NN1: Row 382 | NO1: Row 383 | NP1: Row 384 | NQ1: Row 385 | NR1: Row 386 | NS1: Row 387 | NT1: Row 388 | NU1: Row 389 | NV1: Row 390 | NW1: Row 391 | NX1: Row 392 | NY1: Row 393 | NZ1: Row 394 | OA1: Row 395 | OB1: Row 396 | OC1: Row 397 | OD1: Row 398 | OE1: Row 399 | OF1: Row 400 | OG1: Row 401 | OH1: Row 402 | OI1: Row 403 | OJ1: Row 404 | OK1: Row 405 | OL1: Row 406 | OM1: Row 407 | ON1: Row 408 | OO1: Row 409 | OP1: Row 410 | OQ1: Row 411 | OR1: Row 412 | OS1: Row 413 | OT1: Row 414 | OU1: Row 415 | OV1: Row 416 | OW1: Row 417 | OX1: Row 418 | OY1: Row 419 | OZ1: Row 420 | PA1: Row 421 | PB1: Row 422 | PC1: Row 423 | PD1: Row 424 | PE1: Row 425 | PF1: Row 426 | PG1: Row 427 | PH1: Row 428 | PI1: Row 429 | PJ1: Row 430 | PK1: Row 431 | PL1: Row 432 | PM1: Row 433 | PN1: Row 434 | PO1: Row 435 | PP1: Row 436 | PQ1: Row 437 | PR1: Row 438 | PS1: Row 439 | PT1: Row 440 | PU1: Row 441 | PV1: Row 442 | PW1: Row 443 | PX1: Row 444 | PY1: Row 445 | PZ1: Row 446 | QA1: Row 447 | QB1: Row 448 | QC1: Row 449 | QD1: Row 450 | QE1: Row 451 | QF1: Row 452 | QG1: Row 453 | QH1: Row 454 | QI1: Row 455 | QJ1: Row 456 | QK1: Row 457 | QL1: Row 458 | QM1: Row 459 | QN1: Row 460 | QO1: Row 461 | QP1: Row 462 | QQ1: Row 463 | QR1: Row 464 | QS1: Row 465 | QT1: Row 466 | QU1: Row 467 | QV1: Row 468 | QW1: Row 469 | QX1: Row 470 | QY1: Row 471 | QZ1: Row 472 | RA1: Row 473 | RB1: Row 474 | RC1: Row 475 | RD1: Row 476 | RE1: Row 477 | RF1: Row 478 | RG1: Row 479 | RH1: Row 480 | RI1: Row 481 | RJ1: Row 482 | RK1: Row 483 | RL1: Row 484 | RM1: Row 485 | RN1: Row 486 | RO1: Row 487 | RP1: Row 488 | RQ1: Row 489 | RR1: Row 490 | RS1: Row 491 | RT1: Row 492 | RU1: Row 493 | RV1: Row 494 | RW1: Row 495 | RX1: Row 496 | RY1: Row 497 | RZ1: Row 498 | SA1: Row 499 | SB1: Row 500 | SC1: Row 501 | SD1: Row 502 | SE1: Row 503 | SF1: Row 504
A2: =IF('Loan Due Import'!$B5="",EmployeeNames,_xlfn._xlws.FILTER(EmployeeNames,ISNUMBER(SEARCH('Loan Due Import'!$B5,EmployeeNames)),EmployeeNames)) -> ACOSTA, ANNE GELLE BRIDGITTE GABUTEN | B2: =IF('Loan Due Import'!$B6="",EmployeeNames,_xlfn._xlws.FILTER(EmployeeNames,ISNUMBER(SEARCH('Loan Due Import'!$B6,EmployeeNames)),EmployeeNames)) -> ACOSTA, ANNE GELLE BRIDGITTE GABUTEN | C2: =IF('Loan Due Import'!$B7="",EmployeeNames,_xlfn._xlws.FILTER(EmployeeNames,ISNUMBER(SEARCH('Loan Due Import'!$B7,EmployeeNames)),EmployeeNames)) -> AGBAYANI, ELYKA LAURECE DOROYAN | D2: =IF('Loan Due Import'!$B8="",EmployeeNames,_xlfn._xlws.FILTER(EmployeeNames,ISNUMBER(SEARCH('Loan Due Import'!$B8,EmployeeNames)),EmployeeNames)) -> AGTANG, RHONA MHEA JOY ASUNCION | E2: =IF('Loan Due Import'!$B9="",EmployeeNames,_xlfn._xlws.FILTER(EmployeeNames,ISNUMBER(SEARCH('Loan Due Import'!$B9,EmployeeNames)),EmployeeNames)) -> AGULAY, DENNIS MANGLAL-LAN | F2: =IF('Loan Due Import'!$B10="",EmployeeNames,_xlfn._xlws.FILTER(EmployeeNames,ISNUMBER(SEARCH('Loan Due Import'!$B10,EmployeeNames)),EmployeeNames)) -> ACOSTA, GENEVE ANDRES | G2: =IF('Loan Due Import'!$B11="",EmployeeNames,_xlfn._xlws.FILTER(EmployeeNames,ISNUMBER(SEARCH('Loan Due Import'!$B11,EmployeeNames)),EmployeeNames)) -> CALACAL, CARLA NIÑA SADORRA | H2: =IF('Loan Due Import'!$B12="",EmployeeNames,_xlfn._xlws.FILTER(EmployeeNames,ISNUMBER(SEARCH('Loan Due Import'!$B12,EmployeeNames)),EmployeeNames)) -> DANCEL, CHRISTIAN JAMES BUENO | I2: =IF('Loan Due Import'!$B13="",EmployeeNames,_xlfn._xlws.FILTER(EmployeeNames,ISNUMBER(SEARCH('Loan Due Import'!$B13,EmployeeNames)),EmployeeNames)) -> ASUNCION, JOSEPH DARIANO | J2: =IF('Loan Due Import'!$B14="",EmployeeNames,_xlfn._xlws.FILTER(EmployeeNames,ISNUMBER(SEARCH('Loan Due Import'!$B14,EmployeeNames)),EmployeeNames)) -> DUQUE, DAYZELLE MOLINES | K2: =IF('Loan Due Import'!$B15="",EmployeeNames,_xlfn._xlws.FILTER(EmployeeNames,ISNUMBER(SEARCH('Loan Due Import'!$B15,EmployeeNames)),EmployeeNames)) -> EDNILAO, CHRISTIAN PAUL FUERTES | L2: =IF('Loan Due Import'!$B16="",EmployeeNames,_xlfn._xlws.FILTER(EmployeeNames,ISNUMBER(SEARCH('Loan Due Import'!$B16,EmployeeNames)),EmployeeNames)) -> FORMOSO, RAY VINCENT FLORES | M2: =IF('Loan Due Import'!$B17="",EmployeeNames,_xlfn._xlws.FILTER(EmployeeNames,ISNUMBER(SEARCH('Loan Due Import'!$B17,EmployeeNames)),EmployeeNames)) -> ABAD, FLORIDA RAMOS | N2: =IF('Loan Due Import'!$B18="",EmployeeNames,_xlfn._xlws.FILTER(EmployeeNames,ISNUMBER(SEARCH('Loan Due Import'!$B18,EmployeeNames)),EmployeeNames)) -> ABAD, FLORIDA RAMOS | O2: =IF('Loan Due Import'!$B19="",EmployeeNames,_xlfn._xlws.FILTER(EmployeeNames,ISNUMBER(SEARCH('Loan Due Import'!$B19,EmployeeNames)),EmployeeNames)) -> ABAD, FLORIDA RAMOS | P2: =IF('Loan Due Import'!$B20="",EmployeeNames,_xlfn._xlws.FILTER(EmployeeNames,ISNUMBER(SEARCH('Loan Due Import'!$B20,EmployeeNames)),EmployeeNames)) -> ABAD, FLORIDA RAMOS | Q2: =IF('Loan Due Import'!$B21="",EmployeeNames,_xlfn._xlws.FILTER(EmployeeNames,ISNUMBER(SEARCH('Loan Due Import'!$B21,EmployeeNames)),EmployeeNames)) -> ABAD, FLORIDA RAMOS | R2: =IF('Loan Due Import'!$B22="",EmployeeNames,_xlfn._xlws.FILTER(EmployeeNames,ISNUMBER(SEARCH('Loan Due Import'!$B22,EmployeeNames)),EmployeeNames)) -> ABAD, FLORIDA RAMOS | S2: =IF('Loan Due Import'!$B23="",EmployeeNames,_xlfn._xlws.FILTER(EmployeeNames,ISNUMBER(SEARCH('Loan Due Import'!$B23,EmployeeNames)),EmployeeNames)) -> ABAD, FLORIDA RAMOS | T2: =IF('Loan Due Import'!$B24="",EmployeeNames,_xlfn._xlws.FILTER(EmployeeNames,ISNUMBER(SEARCH('Loan Due Import'!$B24,EmployeeNames)),EmployeeNames)) -> ABAD, FLORIDA RAMOS | U2: =IF('Loan Due Import'!$B25="",EmployeeNames,_xlfn._xlws.FILTER(EmployeeNames,ISNUMBER(SEARCH('Loan Due Import'!$B25,EmployeeNames)),EmployeeNames)) -> ABAD, FLORIDA RAMOS | V2: =IF('Loan Due Import'!$B26="",EmployeeNames,_xlfn._xlws.FILTER(EmployeeNames,ISNUMBER(SEARCH('Loan Due Import'!$B26,EmployeeNames)),EmployeeNames)) -> ABAD, FLORIDA RAMOS | W2: =IF('Loan Due Import'!$B27="",EmployeeNames,_xlfn._xlws.FILTER(EmployeeNames,ISNUMBER(SEARCH('Loan Due Import'!$B27,EmployeeNames)),EmployeeNames)) -> ABAD, FLORIDA RAMOS | X2: =IF('Loan Due Import'!$B28="",EmployeeNames,_xlfn._xlws.FILTER(EmployeeNames,ISNUMBER(SEARCH('Loan Due Import'!$B28,EmployeeNames)),EmployeeNames)) -> ABAD, FLORIDA RAMOS | Y2: =IF('Loan Due Import'!$B29="",EmployeeNames,_xlfn._xlws.FILTER(EmployeeNames,ISNUMBER(SEARCH('Loan Due Import'!$B29,EmployeeNames)),EmployeeNames)) -> ABAD, FLORIDA RAMOS | Z2: =IF('Loan Due Import'!$B30="",EmployeeNames,_xlfn._xlws.FILTER(EmployeeNames,ISNUMBER(SEARCH('Loan Due Import'!$B30,EmployeeNames)),EmployeeNames)) -> ABAD, FLORIDA RAMOS | AA2: =IF('Loan Due Import'!$B31="",EmployeeNames,_xlfn._xlws.FILTER(EmployeeNames,ISNUMBER(SEARCH('Loan Due Import'!$B31,EmployeeNames)),EmployeeNames)) -> ABAD, FLORIDA RAMOS | AB2: =IF('Loan Due Import'!$B32="",EmployeeNames,_xlfn._xlws.FILTER(EmployeeNames,ISNUMBER(SEARCH('Loan Due Import'!$B32,EmployeeNames)),EmployeeNames)) -> ABAD, FLORIDA RAMOS | AC2: =IF('Loan Due Import'!$B33="",EmployeeNames,_xlfn._xlws.FILTER(EmployeeNames,ISNUMBER(SEARCH('Loan Due Import'!$B33,EmployeeNames)),EmployeeNames)) -> ABAD, FLORIDA RAMOS | AD2: =IF('Loan Due Import'!$B34="",EmployeeNames,_xlfn._xlws.FILTER(EmployeeNames,ISNUMBER(SEARCH('Loan Due Import'!$B34,EmployeeNames)),EmployeeNames)) -> ABAD, FLORIDA RAMOS | AE2: =IF('Loan Due Import'!$B35="",EmployeeNames,_xlfn._xlws.FILTER(EmployeeNames,ISNUMBER(SEARCH('Loan Due Import'!$B35,EmployeeNames)),EmployeeNames)) -> ABAD, FLORIDA RAMOS | AF2: =IF('Loan Due Import'!$B36="",EmployeeNames,_xlfn._xlws.FILTER(EmployeeNames,ISNUMBER(SEARCH('Loan Due Import'!$B36,EmployeeNames)),EmployeeNames)) -> ABAD, FLORIDA RAMOS | AG2: =IF('Loan Due Import'!$B37="",EmployeeNames,_xlfn._xlws.FILTER(EmployeeNames,ISNUMBER(SEARCH('Loan Due Import'!$B37,EmployeeNames)),EmployeeNames)) -> ABAD, FLORIDA RAMOS | AH2: =IF('Loan Due Import'!$B38="",EmployeeNames,_xlfn._xlws.FILTER(EmployeeNames,ISNUMBER(SEARCH('Loan Due Import'!$B38,EmployeeNames)),EmployeeNames)) -> ABAD, FLORIDA RAMOS | AI2: =IF('Loan Due Import'!$B39="",EmployeeNames,_xlfn._xlws.FILTER(EmployeeNames,ISNUMBER(SEARCH('Loan Due Import'!$B39,EmployeeNames)),EmployeeNames)) -> ABAD, FLORIDA RAMOS | AJ2: =IF('Loan Due Import'!$B40="",EmployeeNames,_xlfn._xlws.FILTER(EmployeeNames,ISNUMBER(SEARCH('Loan Due Import'!$B40,EmployeeNames)),EmployeeNames)) -> ABAD, FLORIDA RAMOS | AK2: =IF('Loan Due Import'!$B41="",EmployeeNames,_xlfn._xlws.FILTER(EmployeeNames,ISNUMBER(SEARCH('Loan Due Import'!$B41,EmployeeNames)),EmployeeNames)) -> ABAD, FLORIDA RAMOS | AL2: =IF('Loan Due Import'!$B42="",EmployeeNames,_xlfn._xlws.FILTER(EmployeeNames,ISNUMBER(SEARCH('Loan Due Import'!$B42,EmployeeNames)),EmployeeNames)) -> ABAD, FLORIDA RAMOS | AM2: =IF('Loan Due Import'!$B43="",EmployeeNames,_xlfn._xlws.FILTER(EmployeeNames,ISNUMBER(SEARCH('Loan Due Import'!$B43,EmployeeNames)),EmployeeNames)) -> ABAD, FLORIDA RAMOS | AN2: =IF('Loan Due Import'!$B44="",EmployeeNames,_xlfn._xlws.FILTER(EmployeeNames,ISNUMBER(SEARCH('Loan Due Import'!$B44,EmployeeNames)),EmployeeNames)) -> ABAD, FLORIDA RAMOS | AO2: =IF('Loan Due Import'!$B45="",EmployeeNames,_xlfn._xlws.FILTER(EmployeeNames,ISNUMBER(SEARCH('Loan Due Import'!$B45,EmployeeNames)),EmployeeNames)) -> ABAD, FLORIDA RAMOS | AP2: =IF('Loan Due Import'!$B46="",EmployeeNames,_xlfn._xlws.FILTER(EmployeeNames,ISNUMBER(SEARCH('Loan Due Import'!$B46,EmployeeNames)),EmployeeNames)) -> ABAD, FLORIDA RAMOS | AQ2: =IF('Loan Due Import'!$B47="",EmployeeNames,_xlfn._xlws.FILTER(EmployeeNames,ISNUMBER(SEARCH('Loan Due Import'!$B47,EmployeeNames)),EmployeeNames)) -> ABAD, FLORIDA RAMOS | AR2: =IF('Loan Due Import'!$B48="",EmployeeNames,_xlfn._xlws.FILTER(EmployeeNames,ISNUMBER(SEARCH('Loan Due Import'!$B48,EmployeeNames)),EmployeeNames)) -> ABAD, FLORIDA RAMOS | AS2: =IF('Loan Due Import'!$B49="",EmployeeNames,_xlfn._xlws.FILTER(EmployeeNames,ISNUMBER(SEARCH('Loan Due Import'!$B49,EmployeeNames)),EmployeeNames)) -> ABAD, FLORIDA RAMOS | AT2: =IF('Loan Due Import'!$B50="",EmployeeNames,_xlfn._xlws.FILTER(EmployeeNames,ISNUMBER(SEARCH('Loan Due Import'!$B50,EmployeeNames)),EmployeeNames)) -> ABAD, FLORIDA RAMOS | AU2: =IF('Loan Due Import'!$B51="",EmployeeNames,_xlfn._xlws.FILTER(EmployeeNames,ISNUMBER(SEARCH('Loan Due Import'!$B51,EmployeeNames)),EmployeeNames)) -> ABAD, FLORIDA RAMOS | AV2: =IF('Loan Due Import'!$B52="",EmployeeNames,_xlfn._xlws.FILTER(EmployeeNames,ISNUMBER(SEARCH('Loan Due Import'!$B52,EmployeeNames)),EmployeeNames)) -> ABAD, FLORIDA RAMOS | AW2: =IF('Loan Due Import'!$B53="",EmployeeNames,_xlfn._xlws.FILTER(EmployeeNames,ISNUMBER(SEARCH('Loan Due Import'!$B53,EmployeeNames)),EmployeeNames)) -> ABAD, FLORIDA RAMOS | AX2: =IF('Loan Due Import'!$B54="",EmployeeNames,_xlfn._xlws.FILTER(EmployeeNames,ISNUMBER(SEARCH('Loan Due Import'!$B54,EmployeeNames)),EmployeeNames)) -> ABAD, FLORIDA RAMOS | AY2: =IF('Loan Due Import'!$B55="",EmployeeNames,_xlfn._xlws.FILTER(EmployeeNames,ISNUMBER(SEARCH('Loan Due Import'!$B55,EmployeeNames)),EmployeeNames)) -> ABAD, FLORIDA RAMOS | AZ2: =IF('Loan Due Import'!$B56="",EmployeeNames,_xlfn._xlws.FILTER(EmployeeNames,ISNUMBER(SEARCH('Loan Due Import'!$B56,EmployeeNames)),EmployeeNames)) -> ABAD, FLORIDA RAMOS | BA2: =IF('Loan Due Import'!$B57="",EmployeeNames,_xlfn._xlws.FILTER(EmployeeNames,ISNUMBER(SEARCH('Loan Due Import'!$B57,EmployeeNames)),EmployeeNames)) -> ABAD, FLORIDA RAMOS | BB2: =IF('Loan Due Import'!$B58="",EmployeeNames,_xlfn._xlws.FILTER(EmployeeNames,ISNUMBER(SEARCH('Loan Due Import'!$B58,EmployeeNames)),EmployeeNames)) -> ABAD, FLORIDA RAMOS | BC2: =IF('Loan Due Import'!$B59="",EmployeeNames,_xlfn._xlws.FILTER(EmployeeNames,ISNUMBER(SEARCH('Loan Due Import'!$B59,EmployeeNames)),EmployeeNames)) -> ABAD, FLORIDA RAMOS | BD2: =IF('Loan Due Import'!$B60="",EmployeeNames,_xlfn._xlws.FILTER(EmployeeNames,ISNUMBER(SEARCH('Loan Due Import'!$B60,EmployeeNames)),EmployeeNames)) -> ABAD, FLORIDA RAMOS | BE2: =IF('Loan Due Import'!$B61="",EmployeeNames,_xlfn._xlws.FILTER(EmployeeNames,ISNUMBER(SEARCH('Loan Due Import'!$B61,EmployeeNames)),EmployeeNames)) -> ABAD, FLORIDA RAMOS | BF2: =IF('Loan Due Import'!$B62="",EmployeeNames,_xlfn._xlws.FILTER(EmployeeNames,ISNUMBER(SEARCH('Loan Due Import'!$B62,EmployeeNames)),EmployeeNames)) -> ABAD, FLORIDA RAMOS | BG2: =IF('Loan Due Import'!$B63="",EmployeeNames,_xlfn._xlws.FILTER(EmployeeNames,ISNUMBER(SEARCH('Loan Due Import'!$B63,EmployeeNames)),EmployeeNames)) -> ABAD, FLORIDA RAMOS | BH2: =IF('Loan Due Import'!$B64="",EmployeeNames,_xlfn._xlws.FILTER(EmployeeNames,ISNUMBER(SEARCH('Loan Due Import'!$B64,EmployeeNames)),EmployeeNames)) -> ABAD, FLORIDA RAMOS | BI2: =IF('Loan Due Import'!$B65="",EmployeeNames,_xlfn._xlws.FILTER(EmployeeNames,ISNUMBER(SEARCH('Loan Due Import'!$B65,EmployeeNames)),EmployeeNames)) -> ABAD, FLORIDA RAMOS | BJ2: =IF('Loan Due Import'!$B66="",EmployeeNames,_xlfn._xlws.FILTER(EmployeeNames,ISNUMBER(SEARCH('Loan Due Import'!$B66,EmployeeNames)),EmployeeNames)) -> ABAD, FLORIDA RAMOS | BK2: =IF('Loan Due Import'!$B67="",EmployeeNames,_xlfn._xlws.FILTER(EmployeeNames,ISNUMBER(SEARCH('Loan Due Import'!$B67,EmployeeNames)),EmployeeNames)) -> ABAD, FLORIDA RAMOS | BL2: =IF('Loan Due Import'!$B68="",EmployeeNames,_xlfn._xlws.FILTER(EmployeeNames,ISNUMBER(SEARCH('Loan Due Import'!$B68,EmployeeNames)),EmployeeNames)) -> ABAD, FLORIDA RAMOS | BM2: =IF('Loan Due Import'!$B69="",EmployeeNames,_xlfn._xlws.FILTER(EmployeeNames,ISNUMBER(SEARCH('Loan Due Import'!$B69,EmployeeNames)),EmployeeNames)) -> ABAD, FLORIDA RAMOS | BN2: =IF('Loan Due Import'!$B70="",EmployeeNames,_xlfn._xlws.FILTER(EmployeeNames,ISNUMBER(SEARCH('Loan Due Import'!$B70,EmployeeNames)),EmployeeNames)) -> ABAD, FLORIDA RAMOS | BO2: =IF('Loan Due Import'!$B71="",EmployeeNames,_xlfn._xlws.FILTER(EmployeeNames,ISNUMBER(SEARCH('Loan Due Import'!$B71,EmployeeNames)),EmployeeNames)) -> ABAD, FLORIDA RAMOS | BP2: =IF('Loan Due Import'!$B72="",EmployeeNames,_xlfn._xlws.FILTER(EmployeeNames,ISNUMBER(SEARCH('Loan Due Import'!$B72,EmployeeNames)),EmployeeNames)) -> ABAD, FLORIDA RAMOS | BQ2: =IF('Loan Due Import'!$B73="",EmployeeNames,_xlfn._xlws.FILTER(EmployeeNames,ISNUMBER(SEARCH('Loan Due Import'!$B73,EmployeeNames)),EmployeeNames)) -> ABAD, FLORIDA RAMOS | BR2: =IF('Loan Due Import'!$B74="",EmployeeNames,_xlfn._xlws.FILTER(EmployeeNames,ISNUMBER(SEARCH('Loan Due Import'!$B74,EmployeeNames)),EmployeeNames)) -> ABAD, FLORIDA RAMOS | BS2: =IF('Loan Due Import'!$B75="",EmployeeNames,_xlfn._xlws.FILTER(EmployeeNames,ISNUMBER(SEARCH('Loan Due Import'!$B75,EmployeeNames)),EmployeeNames)) -> ABAD, FLORIDA RAMOS | BT2: =IF('Loan Due Import'!$B76="",EmployeeNames,_xlfn._xlws.FILTER(EmployeeNames,ISNUMBER(SEARCH('Loan Due Import'!$B76,EmployeeNames)),EmployeeNames)) -> ABAD, FLORIDA RAMOS | BU2: =IF('Loan Due Import'!$B77="",EmployeeNames,_xlfn._xlws.FILTER(EmployeeNames,ISNUMBER(SEARCH('Loan Due Import'!$B77,EmployeeNames)),EmployeeNames)) -> ABAD, FLORIDA RAMOS | BV2: =IF('Loan Due Import'!$B78="",EmployeeNames,_xlfn._xlws.FILTER(EmployeeNames,ISNUMBER(SEARCH('Loan Due Import'!$B78,EmployeeNames)),EmployeeNames)) -> ABAD, FLORIDA RAMOS | BW2: =IF('Loan Due Import'!$B79="",EmployeeNames,_xlfn._xlws.FILTER(EmployeeNames,ISNUMBER(SEARCH('Loan Due Import'!$B79,EmployeeNames)),EmployeeNames)) -> ABAD, FLORIDA RAMOS | BX2: =IF('Loan Due Import'!$B80="",EmployeeNames,_xlfn._xlws.FILTER(EmployeeNames,ISNUMBER(SEARCH('Loan Due Import'!$B80,EmployeeNames)),EmployeeNames)) -> ABAD, FLORIDA RAMOS | BY2: =IF('Loan Due Import'!$B81="",EmployeeNames,_xlfn._xlws.FILTER(EmployeeNames,ISNUMBER(SEARCH('Loan Due Import'!$B81,EmployeeNames)),EmployeeNames)) -> ABAD, FLORIDA RAMOS | BZ2: =IF('Loan Due Import'!$B82="",EmployeeNames,_xlfn._xlws.FILTER(EmployeeNames,ISNUMBER(SEARCH('Loan Due Import'!$B82,EmployeeNames)),EmployeeNames)) -> ABAD, FLORIDA RAMOS | CA2: =IF('Loan Due Import'!$B83="",EmployeeNames,_xlfn._xlws.FILTER(EmployeeNames,ISNUMBER(SEARCH('Loan Due Import'!$B83,EmployeeNames)),EmployeeNames)) -> ABAD, FLORIDA RAMOS | CB2: =IF('Loan Due Import'!$B84="",EmployeeNames,_xlfn._xlws.FILTER(EmployeeNames,ISNUMBER(SEARCH('Loan Due Import'!$B84,EmployeeNames)),EmployeeNames)) -> ABAD, FLORIDA RAMOS | CC2: =IF('Loan Due Import'!$B85="",EmployeeNames,_xlfn._xlws.FILTER(EmployeeNames,ISNUMBER(SEARCH('Loan Due Import'!$B85,EmployeeNames)),EmployeeNames)) -> ABAD, FLORIDA RAMOS | CD2: =IF('Loan Due Import'!$B86="",EmployeeNames,_xlfn._xlws.FILTER(EmployeeNames,ISNUMBER(SEARCH('Loan Due Import'!$B86,EmployeeNames)),EmployeeNames)) -> ABAD, FLORIDA RAMOS | CE2: =IF('Loan Due Import'!$B87="",EmployeeNames,_xlfn._xlws.FILTER(EmployeeNames,ISNUMBER(SEARCH('Loan Due Import'!$B87,EmployeeNames)),EmployeeNames)) -> ABAD, FLORIDA RAMOS | CF2: =IF('Loan Due Import'!$B88="",EmployeeNames,_xlfn._xlws.FILTER(EmployeeNames,ISNUMBER(SEARCH('Loan Due Import'!$B88,EmployeeNames)),EmployeeNames)) -> ABAD, FLORIDA RAMOS | CG2: =IF('Loan Due Import'!$B89="",EmployeeNames,_xlfn._xlws.FILTER(EmployeeNames,ISNUMBER(SEARCH('Loan Due Import'!$B89,EmployeeNames)),EmployeeNames)) -> ABAD, FLORIDA RAMOS | CH2: =IF('Loan Due Import'!$B90="",EmployeeNames,_xlfn._xlws.FILTER(EmployeeNames,ISNUMBER(SEARCH('Loan Due Import'!$B90,EmployeeNames)),EmployeeNames)) -> ABAD, FLORIDA RAMOS | CI2: =IF('Loan Due Import'!$B91="",EmployeeNames,_xlfn._xlws.FILTER(EmployeeNames,ISNUMBER(SEARCH('Loan Due Import'!$B91,EmployeeNames)),EmployeeNames)) -> ABAD, FLORIDA RAMOS | CJ2: =IF('Loan Due Import'!$B92="",EmployeeNames,_xlfn._xlws.FILTER(EmployeeNames,ISNUMBER(SEARCH('Loan Due Import'!$B92,EmployeeNames)),EmployeeNames)) -> ABAD, FLORIDA RAMOS | CK2: =IF('Loan Due Import'!$B93="",EmployeeNames,_xlfn._xlws.FILTER(EmployeeNames,ISNUMBER(SEARCH('Loan Due Import'!$B93,EmployeeNames)),EmployeeNames)) -> ABAD, FLORIDA RAMOS | CL2: =IF('Loan Due Import'!$B94="",EmployeeNames,_xlfn._xlws.FILTER(EmployeeNames,ISNUMBER(SEARCH('Loan Due Import'!$B94,EmployeeNames)),EmployeeNames)) -> ABAD, FLORIDA RAMOS | CM2: =IF('Loan Due Import'!$B95="",EmployeeNames,_xlfn._xlws.FILTER(EmployeeNames,ISNUMBER(SEARCH('Loan Due Import'!$B95,EmployeeNames)),EmployeeNames)) -> ABAD, FLORIDA RAMOS | CN2: =IF('Loan Due Import'!$B96="",EmployeeNames,_xlfn._xlws.FILTER(EmployeeNames,ISNUMBER(SEARCH('Loan Due Import'!$B96,EmployeeNames)),EmployeeNames)) -> ABAD, FLORIDA RAMOS | CO2: =IF('Loan Due Import'!$B97="",EmployeeNames,_xlfn._xlws.FILTER(EmployeeNames,ISNUMBER(SEARCH('Loan Due Import'!$B97,EmployeeNames)),EmployeeNames)) -> ABAD, FLORIDA RAMOS | CP2: =IF('Loan Due Import'!$B98="",EmployeeNames,_xlfn._xlws.FILTER(EmployeeNames,ISNUMBER(SEARCH('Loan Due Import'!$B98,EmployeeNames)),EmployeeNames)) -> ABAD, FLORIDA RAMOS | CQ2: =IF('Loan Due Import'!$B99="",EmployeeNames,_xlfn._xlws.FILTER(EmployeeNames,ISNUMBER(SEARCH('Loan Due Import'!$B99,EmployeeNames)),EmployeeNames)) -> ABAD, FLORIDA RAMOS | CR2: =IF('Loan Due Import'!$B100="",EmployeeNames,_xlfn._xlws.FILTER(EmployeeNames,ISNUMBER(SEARCH('Loan Due Import'!$B100,EmployeeNames)),EmployeeNames)) -> ABAD, FLORIDA RAMOS | CS2: =IF('Loan Due Import'!$B101="",EmployeeNames,_xlfn._xlws.FILTER(EmployeeNames,ISNUMBER(SEARCH('Loan Due Import'!$B101,EmployeeNames)),EmployeeNames)) -> ABAD, FLORIDA RAMOS | CT2: =IF('Loan Due Import'!$B102="",EmployeeNames,_xlfn._xlws.FILTER(EmployeeNames,ISNUMBER(SEARCH('Loan Due Import'!$B102,EmployeeNames)),EmployeeNames)) -> ABAD, FLORIDA RAMOS | CU2: =IF('Loan Due Import'!$B103="",EmployeeNames,_xlfn._xlws.FILTER(EmployeeNames,ISNUMBER(SEARCH('Loan Due Import'!$B103,EmployeeNames)),EmployeeNames)) -> ABAD, FLORIDA RAMOS | CV2: =IF('Loan Due Import'!$B104="",EmployeeNames,_xlfn._xlws.FILTER(EmployeeNames,ISNUMBER(SEARCH('Loan Due Import'!$B104,EmployeeNames)),EmployeeNames)) -> ABAD, FLORIDA RAMOS | CW2: =IF('Loan Due Import'!$B105="",EmployeeNames,_xlfn._xlws.FILTER(EmployeeNames,ISNUMBER(SEARCH('Loan Due Import'!$B105,EmployeeNames)),EmployeeNames)) -> ABAD, FLORIDA RAMOS | CX2: =IF('Loan Due Import'!$B106="",EmployeeNames,_xlfn._xlws.FILTER(EmployeeNames,ISNUMBER(SEARCH('Loan Due Import'!$B106,EmployeeNames)),EmployeeNames)) -> ABAD, FLORIDA RAMOS | CY2: =IF('Loan Due Import'!$B107="",EmployeeNames,_xlfn._xlws.FILTER(EmployeeNames,ISNUMBER(SEARCH('Loan Due Import'!$B107,EmployeeNames)),EmployeeNames)) -> ABAD, FLORIDA RAMOS | CZ2: =IF('Loan Due Import'!$B108="",EmployeeNames,_xlfn._xlws.FILTER(EmployeeNames,ISNUMBER(SEARCH('Loan Due Import'!$B108,EmployeeNames)),EmployeeNames)) -> ABAD, FLORIDA RAMOS | DA2: =IF('Loan Due Import'!$B109="",EmployeeNames,_xlfn._xlws.FILTER(EmployeeNames,ISNUMBER(SEARCH('Loan Due Import'!$B109,EmployeeNames)),EmployeeNames)) -> ABAD, FLORIDA RAMOS | DB2: =IF('Loan Due Import'!$B110="",EmployeeNames,_xlfn._xlws.FILTER(EmployeeNames,ISNUMBER(SEARCH('Loan Due Import'!$B110,EmployeeNames)),EmployeeNames)) -> ABAD, FLORIDA RAMOS | DC2: =IF('Loan Due Import'!$B111="",EmployeeNames,_xlfn._xlws.FILTER(EmployeeNames,ISNUMBER(SEARCH('Loan Due Import'!$B111,EmployeeNames)),EmployeeNames)) -> ABAD, FLORIDA RAMOS | DD2: =IF('Loan Due Import'!$B112="",EmployeeNames,_xlfn._xlws.FILTER(EmployeeNames,ISNUMBER(SEARCH('Loan Due Import'!$B112,EmployeeNames)),EmployeeNames)) -> ABAD, FLORIDA RAMOS | DE2: =IF('Loan Due Import'!$B113="",EmployeeNames,_xlfn._xlws.FILTER(EmployeeNames,ISNUMBER(SEARCH('Loan Due Import'!$B113,EmployeeNames)),EmployeeNames)) -> ABAD, FLORIDA RAMOS | DF2: =IF('Loan Due Import'!$B114="",EmployeeNames,_xlfn._xlws.FILTER(EmployeeNames,ISNUMBER(SEARCH('Loan Due Import'!$B114,EmployeeNames)),EmployeeNames)) -> ABAD, FLORIDA RAMOS | DG2: =IF('Loan Due Import'!$B115="",EmployeeNames,_xlfn._xlws.FILTER(EmployeeNames,ISNUMBER(SEARCH('Loan Due Import'!$B115,EmployeeNames)),EmployeeNames)) -> ABAD, FLORIDA RAMOS | DH2: =IF('Loan Due Import'!$B116="",EmployeeNames,_xlfn._xlws.FILTER(EmployeeNames,ISNUMBER(SEARCH('Loan Due Import'!$B116,EmployeeNames)),EmployeeNames)) -> ABAD, FLORIDA RAMOS | DI2: =IF('Loan Due Import'!$B117="",EmployeeNames,_xlfn._xlws.FILTER(EmployeeNames,ISNUMBER(SEARCH('Loan Due Import'!$B117,EmployeeNames)),EmployeeNames)) -> ABAD, FLORIDA RAMOS | DJ2: =IF('Loan Due Import'!$B118="",EmployeeNames,_xlfn._xlws.FILTER(EmployeeNames,ISNUMBER(SEARCH('Loan Due Import'!$B118,EmployeeNames)),EmployeeNames)) -> ABAD, FLORIDA RAMOS | DK2: =IF('Loan Due Import'!$B119="",EmployeeNames,_xlfn._xlws.FILTER(EmployeeNames,ISNUMBER(SEARCH('Loan Due Import'!$B119,EmployeeNames)),EmployeeNames)) -> ABAD, FLORIDA RAMOS | DL2: =IF('Loan Due Import'!$B120="",EmployeeNames,_xlfn._xlws.FILTER(EmployeeNames,ISNUMBER(SEARCH('Loan Due Import'!$B120,EmployeeNames)),EmployeeNames)) -> ABAD, FLORIDA RAMOS | DM2: =IF('Loan Due Import'!$B121="",EmployeeNames,_xlfn._xlws.FILTER(EmployeeNames,ISNUMBER(SEARCH('Loan Due Import'!$B121,EmployeeNames)),EmployeeNames)) -> ABAD, FLORIDA RAMOS | DN2: =IF('Loan Due Import'!$B122="",EmployeeNames,_xlfn._xlws.FILTER(EmployeeNames,ISNUMBER(SEARCH('Loan Due Import'!$B122,EmployeeNames)),EmployeeNames)) -> ABAD, FLORIDA RAMOS | DO2: =IF('Loan Due Import'!$B123="",EmployeeNames,_xlfn._xlws.FILTER(EmployeeNames,ISNUMBER(SEARCH('Loan Due Import'!$B123,EmployeeNames)),EmployeeNames)) -> ABAD, FLORIDA RAMOS | DP2: =IF('Loan Due Import'!$B124="",EmployeeNames,_xlfn._xlws.FILTER(EmployeeNames,ISNUMBER(SEARCH('Loan Due Import'!$B124,EmployeeNames)),EmployeeNames)) -> ABAD, FLORIDA RAMOS | DQ2: =IF('Loan Due Import'!$B125="",EmployeeNames,_xlfn._xlws.FILTER(EmployeeNames,ISNUMBER(SEARCH('Loan Due Import'!$B125,EmployeeNames)),EmployeeNames)) -> ABAD, FLORIDA RAMOS | DR2: =IF('Loan Due Import'!$B126="",EmployeeNames,_xlfn._xlws.FILTER(EmployeeNames,ISNUMBER(SEARCH('Loan Due Import'!$B126,EmployeeNames)),EmployeeNames)) -> ABAD, FLORIDA RAMOS | DS2: =IF('Loan Due Import'!$B127="",EmployeeNames,_xlfn._xlws.FILTER(EmployeeNames,ISNUMBER(SEARCH('Loan Due Import'!$B127,EmployeeNames)),EmployeeNames)) -> ABAD, FLORIDA RAMOS | DT2: =IF('Loan Due Import'!$B128="",EmployeeNames,_xlfn._xlws.FILTER(EmployeeNames,ISNUMBER(SEARCH('Loan Due Import'!$B128,EmployeeNames)),EmployeeNames)) -> ABAD, FLORIDA RAMOS | DU2: =IF('Loan Due Import'!$B129="",EmployeeNames,_xlfn._xlws.FILTER(EmployeeNames,ISNUMBER(SEARCH('Loan Due Import'!$B129,EmployeeNames)),EmployeeNames)) -> ABAD, FLORIDA RAMOS | DV2: =IF('Loan Due Import'!$B130="",EmployeeNames,_xlfn._xlws.FILTER(EmployeeNames,ISNUMBER(SEARCH('Loan Due Import'!$B130,EmployeeNames)),EmployeeNames)) -> ABAD, FLORIDA RAMOS | DW2: =IF('Loan Due Import'!$B131="",EmployeeNames,_xlfn._xlws.FILTER(EmployeeNames,ISNUMBER(SEARCH('Loan Due Import'!$B131,EmployeeNames)),EmployeeNames)) -> ABAD, FLORIDA RAMOS | DX2: =IF('Loan Due Import'!$B132="",EmployeeNames,_xlfn._xlws.FILTER(EmployeeNames,ISNUMBER(SEARCH('Loan Due Import'!$B132,EmployeeNames)),EmployeeNames)) -> ABAD, FLORIDA RAMOS | DY2: =IF('Loan Due Import'!$B133="",EmployeeNames,_xlfn._xlws.FILTER(EmployeeNames,ISNUMBER(SEARCH('Loan Due Import'!$B133,EmployeeNames)),EmployeeNames)) -> ABAD, FLORIDA RAMOS | DZ2: =IF('Loan Due Import'!$B134="",EmployeeNames,_xlfn._xlws.FILTER(EmployeeNames,ISNUMBER(SEARCH('Loan Due Import'!$B134,EmployeeNames)),EmployeeNames)) -> ABAD, FLORIDA RAMOS | EA2: =IF('Loan Due Import'!$B135="",EmployeeNames,_xlfn._xlws.FILTER(EmployeeNames,ISNUMBER(SEARCH('Loan Due Import'!$B135,EmployeeNames)),EmployeeNames)) -> ABAD, FLORIDA RAMOS | EB2: =IF('Loan Due Import'!$B136="",EmployeeNames,_xlfn._xlws.FILTER(EmployeeNames,ISNUMBER(SEARCH('Loan Due Import'!$B136,EmployeeNames)),EmployeeNames)) -> ABAD, FLORIDA RAMOS | EC2: =IF('Loan Due Import'!$B137="",EmployeeNames,_xlfn._xlws.FILTER(EmployeeNames,ISNUMBER(SEARCH('Loan Due Import'!$B137,EmployeeNames)),EmployeeNames)) -> ABAD, FLORIDA RAMOS | ED2: =IF('Loan Due Import'!$B138="",EmployeeNames,_xlfn._xlws.FILTER(EmployeeNames,ISNUMBER(SEARCH('Loan Due Import'!$B138,EmployeeNames)),EmployeeNames)) -> ABAD, FLORIDA RAMOS | EE2: =IF('Loan Due Import'!$B139="",EmployeeNames,_xlfn._xlws.FILTER(EmployeeNames,ISNUMBER(SEARCH('Loan Due Import'!$B139,EmployeeNames)),EmployeeNames)) -> ABAD, FLORIDA RAMOS | EF2: =IF('Loan Due Import'!$B140="",EmployeeNames,_xlfn._xlws.FILTER(EmployeeNames,ISNUMBER(SEARCH('Loan Due Import'!$B140,EmployeeNames)),EmployeeNames)) -> ABAD, FLORIDA RAMOS | EG2: =IF('Loan Due Import'!$B141="",EmployeeNames,_xlfn._xlws.FILTER(EmployeeNames,ISNUMBER(SEARCH('Loan Due Import'!$B141,EmployeeNames)),EmployeeNames)) -> ABAD, FLORIDA RAMOS | EH2: =IF('Loan Due Import'!$B142="",EmployeeNames,_xlfn._xlws.FILTER(EmployeeNames,ISNUMBER(SEARCH('Loan Due Import'!$B142,EmployeeNames)),EmployeeNames)) -> ABAD, FLORIDA RAMOS | EI2: =IF('Loan Due Import'!$B143="",EmployeeNames,_xlfn._xlws.FILTER(EmployeeNames,ISNUMBER(SEARCH('Loan Due Import'!$B143,EmployeeNames)),EmployeeNames)) -> ABAD, FLORIDA RAMOS | EJ2: =IF('Loan Due Import'!$B144="",EmployeeNames,_xlfn._xlws.FILTER(EmployeeNames,ISNUMBER(SEARCH('Loan Due Import'!$B144,EmployeeNames)),EmployeeNames)) -> ABAD, FLORIDA RAMOS | EK2: =IF('Loan Due Import'!$B145="",EmployeeNames,_xlfn._xlws.FILTER(EmployeeNames,ISNUMBER(SEARCH('Loan Due Import'!$B145,EmployeeNames)),EmployeeNames)) -> ABAD, FLORIDA RAMOS | EL2: =IF('Loan Due Import'!$B146="",EmployeeNames,_xlfn._xlws.FILTER(EmployeeNames,ISNUMBER(SEARCH('Loan Due Import'!$B146,EmployeeNames)),EmployeeNames)) -> ABAD, FLORIDA RAMOS | EM2: =IF('Loan Due Import'!$B147="",EmployeeNames,_xlfn._xlws.FILTER(EmployeeNames,ISNUMBER(SEARCH('Loan Due Import'!$B147,EmployeeNames)),EmployeeNames)) -> ABAD, FLORIDA RAMOS | EN2: =IF('Loan Due Import'!$B148="",EmployeeNames,_xlfn._xlws.FILTER(EmployeeNames,ISNUMBER(SEARCH('Loan Due Import'!$B148,EmployeeNames)),EmployeeNames)) -> ABAD, FLORIDA RAMOS | EO2: =IF('Loan Due Import'!$B149="",EmployeeNames,_xlfn._xlws.FILTER(EmployeeNames,ISNUMBER(SEARCH('Loan Due Import'!$B149,EmployeeNames)),EmployeeNames)) -> ABAD, FLORIDA RAMOS | EP2: =IF('Loan Due Import'!$B150="",EmployeeNames,_xlfn._xlws.FILTER(EmployeeNames,ISNUMBER(SEARCH('Loan Due Import'!$B150,EmployeeNames)),EmployeeNames)) -> ABAD, FLORIDA RAMOS | EQ2: =IF('Loan Due Import'!$B151="",EmployeeNames,_xlfn._xlws.FILTER(EmployeeNames,ISNUMBER(SEARCH('Loan Due Import'!$B151,EmployeeNames)),EmployeeNames)) -> ABAD, FLORIDA RAMOS | ER2: =IF('Loan Due Import'!$B152="",EmployeeNames,_xlfn._xlws.FILTER(EmployeeNames,ISNUMBER(SEARCH('Loan Due Import'!$B152,EmployeeNames)),EmployeeNames)) -> ABAD, FLORIDA RAMOS | ES2: =IF('Loan Due Import'!$B153="",EmployeeNames,_xlfn._xlws.FILTER(EmployeeNames,ISNUMBER(SEARCH('Loan Due Import'!$B153,EmployeeNames)),EmployeeNames)) -> ABAD, FLORIDA RAMOS | ET2: =IF('Loan Due Import'!$B154="",EmployeeNames,_xlfn._xlws.FILTER(EmployeeNames,ISNUMBER(SEARCH('Loan Due Import'!$B154,EmployeeNames)),EmployeeNames)) -> ABAD, FLORIDA RAMOS | EU2: =IF('Loan Due Import'!$B155="",EmployeeNames,_xlfn._xlws.FILTER(EmployeeNames,ISNUMBER(SEARCH('Loan Due Import'!$B155,EmployeeNames)),EmployeeNames)) -> ABAD, FLORIDA RAMOS | EV2: =IF('Loan Due Import'!$B156="",EmployeeNames,_xlfn._xlws.FILTER(EmployeeNames,ISNUMBER(SEARCH('Loan Due Import'!$B156,EmployeeNames)),EmployeeNames)) -> ABAD, FLORIDA RAMOS | EW2: =IF('Loan Due Import'!$B157="",EmployeeNames,_xlfn._xlws.FILTER(EmployeeNames,ISNUMBER(SEARCH('Loan Due Import'!$B157,EmployeeNames)),EmployeeNames)) -> ABAD, FLORIDA RAMOS | EX2: =IF('Loan Due Import'!$B158="",EmployeeNames,_xlfn._xlws.FILTER(EmployeeNames,ISNUMBER(SEARCH('Loan Due Import'!$B158,EmployeeNames)),EmployeeNames)) -> ABAD, FLORIDA RAMOS | EY2: =IF('Loan Due Import'!$B159="",EmployeeNames,_xlfn._xlws.FILTER(EmployeeNames,ISNUMBER(SEARCH('Loan Due Import'!$B159,EmployeeNames)),EmployeeNames)) -> ABAD, FLORIDA RAMOS | EZ2: =IF('Loan Due Import'!$B160="",EmployeeNames,_xlfn._xlws.FILTER(EmployeeNames,ISNUMBER(SEARCH('Loan Due Import'!$B160,EmployeeNames)),EmployeeNames)) -> ABAD, FLORIDA RAMOS | FA2: =IF('Loan Due Import'!$B161="",EmployeeNames,_xlfn._xlws.FILTER(EmployeeNames,ISNUMBER(SEARCH('Loan Due Import'!$B161,EmployeeNames)),EmployeeNames)) -> ABAD, FLORIDA RAMOS | FB2: =IF('Loan Due Import'!$B162="",EmployeeNames,_xlfn._xlws.FILTER(EmployeeNames,ISNUMBER(SEARCH('Loan Due Import'!$B162,EmployeeNames)),EmployeeNames)) -> ABAD, FLORIDA RAMOS | FC2: =IF('Loan Due Import'!$B163="",EmployeeNames,_xlfn._xlws.FILTER(EmployeeNames,ISNUMBER(SEARCH('Loan Due Import'!$B163,EmployeeNames)),EmployeeNames)) -> ABAD, FLORIDA RAMOS | FD2: =IF('Loan Due Import'!$B164="",EmployeeNames,_xlfn._xlws.FILTER(EmployeeNames,ISNUMBER(SEARCH('Loan Due Import'!$B164,EmployeeNames)),EmployeeNames)) -> ABAD, FLORIDA RAMOS | FE2: =IF('Loan Due Import'!$B165="",EmployeeNames,_xlfn._xlws.FILTER(EmployeeNames,ISNUMBER(SEARCH('Loan Due Import'!$B165,EmployeeNames)),EmployeeNames)) -> ABAD, FLORIDA RAMOS | FF2: =IF('Loan Due Import'!$B166="",EmployeeNames,_xlfn._xlws.FILTER(EmployeeNames,ISNUMBER(SEARCH('Loan Due Import'!$B166,EmployeeNames)),EmployeeNames)) -> ABAD, FLORIDA RAMOS | FG2: =IF('Loan Due Import'!$B167="",EmployeeNames,_xlfn._xlws.FILTER(EmployeeNames,ISNUMBER(SEARCH('Loan Due Import'!$B167,EmployeeNames)),EmployeeNames)) -> ABAD, FLORIDA RAMOS | FH2: =IF('Loan Due Import'!$B168="",EmployeeNames,_xlfn._xlws.FILTER(EmployeeNames,ISNUMBER(SEARCH('Loan Due Import'!$B168,EmployeeNames)),EmployeeNames)) -> ABAD, FLORIDA RAMOS | FI2: =IF('Loan Due Import'!$B169="",EmployeeNames,_xlfn._xlws.FILTER(EmployeeNames,ISNUMBER(SEARCH('Loan Due Import'!$B169,EmployeeNames)),EmployeeNames)) -> ABAD, FLORIDA RAMOS | FJ2: =IF('Loan Due Import'!$B170="",EmployeeNames,_xlfn._xlws.FILTER(EmployeeNames,ISNUMBER(SEARCH('Loan Due Import'!$B170,EmployeeNames)),EmployeeNames)) -> ABAD, FLORIDA RAMOS | FK2: =IF('Loan Due Import'!$B171="",EmployeeNames,_xlfn._xlws.FILTER(EmployeeNames,ISNUMBER(SEARCH('Loan Due Import'!$B171,EmployeeNames)),EmployeeNames)) -> ABAD, FLORIDA RAMOS | FL2: =IF('Loan Due Import'!$B172="",EmployeeNames,_xlfn._xlws.FILTER(EmployeeNames,ISNUMBER(SEARCH('Loan Due Import'!$B172,EmployeeNames)),EmployeeNames)) -> ABAD, FLORIDA RAMOS | FM2: =IF('Loan Due Import'!$B173="",EmployeeNames,_xlfn._xlws.FILTER(EmployeeNames,ISNUMBER(SEARCH('Loan Due Import'!$B173,EmployeeNames)),EmployeeNames)) -> ABAD, FLORIDA RAMOS | FN2: =IF('Loan Due Import'!$B174="",EmployeeNames,_xlfn._xlws.FILTER(EmployeeNames,ISNUMBER(SEARCH('Loan Due Import'!$B174,EmployeeNames)),EmployeeNames)) -> ABAD, FLORIDA RAMOS | FO2: =IF('Loan Due Import'!$B175="",EmployeeNames,_xlfn._xlws.FILTER(EmployeeNames,ISNUMBER(SEARCH('Loan Due Import'!$B175,EmployeeNames)),EmployeeNames)) -> ABAD, FLORIDA RAMOS | FP2: =IF('Loan Due Import'!$B176="",EmployeeNames,_xlfn._xlws.FILTER(EmployeeNames,ISNUMBER(SEARCH('Loan Due Import'!$B176,EmployeeNames)),EmployeeNames)) -> ABAD, FLORIDA RAMOS | FQ2: =IF('Loan Due Import'!$B177="",EmployeeNames,_xlfn._xlws.FILTER(EmployeeNames,ISNUMBER(SEARCH('Loan Due Import'!$B177,EmployeeNames)),EmployeeNames)) -> ABAD, FLORIDA RAMOS | FR2: =IF('Loan Due Import'!$B178="",EmployeeNames,_xlfn._xlws.FILTER(EmployeeNames,ISNUMBER(SEARCH('Loan Due Import'!$B178,EmployeeNames)),EmployeeNames)) -> ABAD, FLORIDA RAMOS | FS2: =IF('Loan Due Import'!$B179="",EmployeeNames,_xlfn._xlws.FILTER(EmployeeNames,ISNUMBER(SEARCH('Loan Due Import'!$B179,EmployeeNames)),EmployeeNames)) -> ABAD, FLORIDA RAMOS | FT2: =IF('Loan Due Import'!$B180="",EmployeeNames,_xlfn._xlws.FILTER(EmployeeNames,ISNUMBER(SEARCH('Loan Due Import'!$B180,EmployeeNames)),EmployeeNames)) -> ABAD, FLORIDA RAMOS | FU2: =IF('Loan Due Import'!$B181="",EmployeeNames,_xlfn._xlws.FILTER(EmployeeNames,ISNUMBER(SEARCH('Loan Due Import'!$B181,EmployeeNames)),EmployeeNames)) -> ABAD, FLORIDA RAMOS | FV2: =IF('Loan Due Import'!$B182="",EmployeeNames,_xlfn._xlws.FILTER(EmployeeNames,ISNUMBER(SEARCH('Loan Due Import'!$B182,EmployeeNames)),EmployeeNames)) -> ABAD, FLORIDA RAMOS | FW2: =IF('Loan Due Import'!$B183="",EmployeeNames,_xlfn._xlws.FILTER(EmployeeNames,ISNUMBER(SEARCH('Loan Due Import'!$B183,EmployeeNames)),EmployeeNames)) -> ABAD, FLORIDA RAMOS | FX2: =IF('Loan Due Import'!$B184="",EmployeeNames,_xlfn._xlws.FILTER(EmployeeNames,ISNUMBER(SEARCH('Loan Due Import'!$B184,EmployeeNames)),EmployeeNames)) -> ABAD, FLORIDA RAMOS | FY2: =IF('Loan Due Import'!$B185="",EmployeeNames,_xlfn._xlws.FILTER(EmployeeNames,ISNUMBER(SEARCH('Loan Due Import'!$B185,EmployeeNames)),EmployeeNames)) -> ABAD, FLORIDA RAMOS | FZ2: =IF('Loan Due Import'!$B186="",EmployeeNames,_xlfn._xlws.FILTER(EmployeeNames,ISNUMBER(SEARCH('Loan Due Import'!$B186,EmployeeNames)),EmployeeNames)) -> ABAD, FLORIDA RAMOS | GA2: =IF('Loan Due Import'!$B187="",EmployeeNames,_xlfn._xlws.FILTER(EmployeeNames,ISNUMBER(SEARCH('Loan Due Import'!$B187,EmployeeNames)),EmployeeNames)) -> ABAD, FLORIDA RAMOS | GB2: =IF('Loan Due Import'!$B188="",EmployeeNames,_xlfn._xlws.FILTER(EmployeeNames,ISNUMBER(SEARCH('Loan Due Import'!$B188,EmployeeNames)),EmployeeNames)) -> ABAD, FLORIDA RAMOS | GC2: =IF('Loan Due Import'!$B189="",EmployeeNames,_xlfn._xlws.FILTER(EmployeeNames,ISNUMBER(SEARCH('Loan Due Import'!$B189,EmployeeNames)),EmployeeNames)) -> ABAD, FLORIDA RAMOS | GD2: =IF('Loan Due Import'!$B190="",EmployeeNames,_xlfn._xlws.FILTER(EmployeeNames,ISNUMBER(SEARCH('Loan Due Import'!$B190,EmployeeNames)),EmployeeNames)) -> ABAD, FLORIDA RAMOS | GE2: =IF('Loan Due Import'!$B191="",EmployeeNames,_xlfn._xlws.FILTER(EmployeeNames,ISNUMBER(SEARCH('Loan Due Import'!$B191,EmployeeNames)),EmployeeNames)) -> ABAD, FLORIDA RAMOS | GF2: =IF('Loan Due Import'!$B192="",EmployeeNames,_xlfn._xlws.FILTER(EmployeeNames,ISNUMBER(SEARCH('Loan Due Import'!$B192,EmployeeNames)),EmployeeNames)) -> ABAD, FLORIDA RAMOS | GG2: =IF('Loan Due Import'!$B193="",EmployeeNames,_xlfn._xlws.FILTER(EmployeeNames,ISNUMBER(SEARCH('Loan Due Import'!$B193,EmployeeNames)),EmployeeNames)) -> ABAD, FLORIDA RAMOS | GH2: =IF('Loan Due Import'!$B194="",EmployeeNames,_xlfn._xlws.FILTER(EmployeeNames,ISNUMBER(SEARCH('Loan Due Import'!$B194,EmployeeNames)),EmployeeNames)) -> ABAD, FLORIDA RAMOS | GI2: =IF('Loan Due Import'!$B195="",EmployeeNames,_xlfn._xlws.FILTER(EmployeeNames,ISNUMBER(SEARCH('Loan Due Import'!$B195,EmployeeNames)),EmployeeNames)) -> ABAD, FLORIDA RAMOS | GJ2: =IF('Loan Due Import'!$B196="",EmployeeNames,_xlfn._xlws.FILTER(EmployeeNames,ISNUMBER(SEARCH('Loan Due Import'!$B196,EmployeeNames)),EmployeeNames)) -> ABAD, FLORIDA RAMOS | GK2: =IF('Loan Due Import'!$B197="",EmployeeNames,_xlfn._xlws.FILTER(EmployeeNames,ISNUMBER(SEARCH('Loan Due Import'!$B197,EmployeeNames)),EmployeeNames)) -> ABAD, FLORIDA RAMOS | GL2: =IF('Loan Due Import'!$B198="",EmployeeNames,_xlfn._xlws.FILTER(EmployeeNames,ISNUMBER(SEARCH('Loan Due Import'!$B198,EmployeeNames)),EmployeeNames)) -> ABAD, FLORIDA RAMOS | GM2: =IF('Loan Due Import'!$B199="",EmployeeNames,_xlfn._xlws.FILTER(EmployeeNames,ISNUMBER(SEARCH('Loan Due Import'!$B199,EmployeeNames)),EmployeeNames)) -> ABAD, FLORIDA RAMOS | GN2: =IF('Loan Due Import'!$B200="",EmployeeNames,_xlfn._xlws.FILTER(EmployeeNames,ISNUMBER(SEARCH('Loan Due Import'!$B200,EmployeeNames)),EmployeeNames)) -> ABAD, FLORIDA RAMOS | GO2: =IF('Loan Due Import'!$B201="",EmployeeNames,_xlfn._xlws.FILTER(EmployeeNames,ISNUMBER(SEARCH('Loan Due Import'!$B201,EmployeeNames)),EmployeeNames)) -> ABAD, FLORIDA RAMOS | GP2: =IF('Loan Due Import'!$B202="",EmployeeNames,_xlfn._xlws.FILTER(EmployeeNames,ISNUMBER(SEARCH('Loan Due Import'!$B202,EmployeeNames)),EmployeeNames)) -> ABAD, FLORIDA RAMOS | GQ2: =IF('Loan Due Import'!$B203="",EmployeeNames,_xlfn._xlws.FILTER(EmployeeNames,ISNUMBER(SEARCH('Loan Due Import'!$B203,EmployeeNames)),EmployeeNames)) -> ABAD, FLORIDA RAMOS | GR2: =IF('Loan Due Import'!$B204="",EmployeeNames,_xlfn._xlws.FILTER(EmployeeNames,ISNUMBER(SEARCH('Loan Due Import'!$B204,EmployeeNames)),EmployeeNames)) -> ABAD, FLORIDA RAMOS | GS2: =IF('Loan Due Import'!$B205="",EmployeeNames,_xlfn._xlws.FILTER(EmployeeNames,ISNUMBER(SEARCH('Loan Due Import'!$B205,EmployeeNames)),EmployeeNames)) -> ABAD, FLORIDA RAMOS | GT2: =IF('Loan Due Import'!$B206="",EmployeeNames,_xlfn._xlws.FILTER(EmployeeNames,ISNUMBER(SEARCH('Loan Due Import'!$B206,EmployeeNames)),EmployeeNames)) -> ABAD, FLORIDA RAMOS | GU2: =IF('Loan Due Import'!$B207="",EmployeeNames,_xlfn._xlws.FILTER(EmployeeNames,ISNUMBER(SEARCH('Loan Due Import'!$B207,EmployeeNames)),EmployeeNames)) -> ABAD, FLORIDA RAMOS | GV2: =IF('Loan Due Import'!$B208="",EmployeeNames,_xlfn._xlws.FILTER(EmployeeNames,ISNUMBER(SEARCH('Loan Due Import'!$B208,EmployeeNames)),EmployeeNames)) -> ABAD, FLORIDA RAMOS | GW2: =IF('Loan Due Import'!$B209="",EmployeeNames,_xlfn._xlws.FILTER(EmployeeNames,ISNUMBER(SEARCH('Loan Due Import'!$B209,EmployeeNames)),EmployeeNames)) -> ABAD, FLORIDA RAMOS | GX2: =IF('Loan Due Import'!$B210="",EmployeeNames,_xlfn._xlws.FILTER(EmployeeNames,ISNUMBER(SEARCH('Loan Due Import'!$B210,EmployeeNames)),EmployeeNames)) -> ABAD, FLORIDA RAMOS | GY2: =IF('Loan Due Import'!$B211="",EmployeeNames,_xlfn._xlws.FILTER(EmployeeNames,ISNUMBER(SEARCH('Loan Due Import'!$B211,EmployeeNames)),EmployeeNames)) -> ABAD, FLORIDA RAMOS | GZ2: =IF('Loan Due Import'!$B212="",EmployeeNames,_xlfn._xlws.FILTER(EmployeeNames,ISNUMBER(SEARCH('Loan Due Import'!$B212,EmployeeNames)),EmployeeNames)) -> ABAD, FLORIDA RAMOS | HA2: =IF('Loan Due Import'!$B213="",EmployeeNames,_xlfn._xlws.FILTER(EmployeeNames,ISNUMBER(SEARCH('Loan Due Import'!$B213,EmployeeNames)),EmployeeNames)) -> ABAD, FLORIDA RAMOS | HB2: =IF('Loan Due Import'!$B214="",EmployeeNames,_xlfn._xlws.FILTER(EmployeeNames,ISNUMBER(SEARCH('Loan Due Import'!$B214,EmployeeNames)),EmployeeNames)) -> ABAD, FLORIDA RAMOS | HC2: =IF('Loan Due Import'!$B215="",EmployeeNames,_xlfn._xlws.FILTER(EmployeeNames,ISNUMBER(SEARCH('Loan Due Import'!$B215,EmployeeNames)),EmployeeNames)) -> ABAD, FLORIDA RAMOS | HD2: =IF('Loan Due Import'!$B216="",EmployeeNames,_xlfn._xlws.FILTER(EmployeeNames,ISNUMBER(SEARCH('Loan Due Import'!$B216,EmployeeNames)),EmployeeNames)) -> ABAD, FLORIDA RAMOS | HE2: =IF('Loan Due Import'!$B217="",EmployeeNames,_xlfn._xlws.FILTER(EmployeeNames,ISNUMBER(SEARCH('Loan Due Import'!$B217,EmployeeNames)),EmployeeNames)) -> ABAD, FLORIDA RAMOS | HF2: =IF('Loan Due Import'!$B218="",EmployeeNames,_xlfn._xlws.FILTER(EmployeeNames,ISNUMBER(SEARCH('Loan Due Import'!$B218,EmployeeNames)),EmployeeNames)) -> ABAD, FLORIDA RAMOS | HG2: =IF('Loan Due Import'!$B219="",EmployeeNames,_xlfn._xlws.FILTER(EmployeeNames,ISNUMBER(SEARCH('Loan Due Import'!$B219,EmployeeNames)),EmployeeNames)) -> ABAD, FLORIDA RAMOS | HH2: =IF('Loan Due Import'!$B220="",EmployeeNames,_xlfn._xlws.FILTER(EmployeeNames,ISNUMBER(SEARCH('Loan Due Import'!$B220,EmployeeNames)),EmployeeNames)) -> ABAD, FLORIDA RAMOS | HI2: =IF('Loan Due Import'!$B221="",EmployeeNames,_xlfn._xlws.FILTER(EmployeeNames,ISNUMBER(SEARCH('Loan Due Import'!$B221,EmployeeNames)),EmployeeNames)) -> ABAD, FLORIDA RAMOS | HJ2: =IF('Loan Due Import'!$B222="",EmployeeNames,_xlfn._xlws.FILTER(EmployeeNames,ISNUMBER(SEARCH('Loan Due Import'!$B222,EmployeeNames)),EmployeeNames)) -> ABAD, FLORIDA RAMOS | HK2: =IF('Loan Due Import'!$B223="",EmployeeNames,_xlfn._xlws.FILTER(EmployeeNames,ISNUMBER(SEARCH('Loan Due Import'!$B223,EmployeeNames)),EmployeeNames)) -> ABAD, FLORIDA RAMOS | HL2: =IF('Loan Due Import'!$B224="",EmployeeNames,_xlfn._xlws.FILTER(EmployeeNames,ISNUMBER(SEARCH('Loan Due Import'!$B224,EmployeeNames)),EmployeeNames)) -> ABAD, FLORIDA RAMOS | HM2: =IF('Loan Due Import'!$B225="",EmployeeNames,_xlfn._xlws.FILTER(EmployeeNames,ISNUMBER(SEARCH('Loan Due Import'!$B225,EmployeeNames)),EmployeeNames)) -> ABAD, FLORIDA RAMOS | HN2: =IF('Loan Due Import'!$B226="",EmployeeNames,_xlfn._xlws.FILTER(EmployeeNames,ISNUMBER(SEARCH('Loan Due Import'!$B226,EmployeeNames)),EmployeeNames)) -> ABAD, FLORIDA RAMOS | HO2: =IF('Loan Due Import'!$B227="",EmployeeNames,_xlfn._xlws.FILTER(EmployeeNames,ISNUMBER(SEARCH('Loan Due Import'!$B227,EmployeeNames)),EmployeeNames)) -> ABAD, FLORIDA RAMOS | HP2: =IF('Loan Due Import'!$B228="",EmployeeNames,_xlfn._xlws.FILTER(EmployeeNames,ISNUMBER(SEARCH('Loan Due Import'!$B228,EmployeeNames)),EmployeeNames)) -> ABAD, FLORIDA RAMOS | HQ2: =IF('Loan Due Import'!$B229="",EmployeeNames,_xlfn._xlws.FILTER(EmployeeNames,ISNUMBER(SEARCH('Loan Due Import'!$B229,EmployeeNames)),EmployeeNames)) -> ABAD, FLORIDA RAMOS | HR2: =IF('Loan Due Import'!$B230="",EmployeeNames,_xlfn._xlws.FILTER(EmployeeNames,ISNUMBER(SEARCH('Loan Due Import'!$B230,EmployeeNames)),EmployeeNames)) -> ABAD, FLORIDA RAMOS | HS2: =IF('Loan Due Import'!$B231="",EmployeeNames,_xlfn._xlws.FILTER(EmployeeNames,ISNUMBER(SEARCH('Loan Due Import'!$B231,EmployeeNames)),EmployeeNames)) -> ABAD, FLORIDA RAMOS | HT2: =IF('Loan Due Import'!$B232="",EmployeeNames,_xlfn._xlws.FILTER(EmployeeNames,ISNUMBER(SEARCH('Loan Due Import'!$B232,EmployeeNames)),EmployeeNames)) -> ABAD, FLORIDA RAMOS | HU2: =IF('Loan Due Import'!$B233="",EmployeeNames,_xlfn._xlws.FILTER(EmployeeNames,ISNUMBER(SEARCH('Loan Due Import'!$B233,EmployeeNames)),EmployeeNames)) -> ABAD, FLORIDA RAMOS | HV2: =IF('Loan Due Import'!$B234="",EmployeeNames,_xlfn._xlws.FILTER(EmployeeNames,ISNUMBER(SEARCH('Loan Due Import'!$B234,EmployeeNames)),EmployeeNames)) -> ABAD, FLORIDA RAMOS | HW2: =IF('Loan Due Import'!$B235="",EmployeeNames,_xlfn._xlws.FILTER(EmployeeNames,ISNUMBER(SEARCH('Loan Due Import'!$B235,EmployeeNames)),EmployeeNames)) -> ABAD, FLORIDA RAMOS | HX2: =IF('Loan Due Import'!$B236="",EmployeeNames,_xlfn._xlws.FILTER(EmployeeNames,ISNUMBER(SEARCH('Loan Due Import'!$B236,EmployeeNames)),EmployeeNames)) -> ABAD, FLORIDA RAMOS | HY2: =IF('Loan Due Import'!$B237="",EmployeeNames,_xlfn._xlws.FILTER(EmployeeNames,ISNUMBER(SEARCH('Loan Due Import'!$B237,EmployeeNames)),EmployeeNames)) -> ABAD, FLORIDA RAMOS | HZ2: =IF('Loan Due Import'!$B238="",EmployeeNames,_xlfn._xlws.FILTER(EmployeeNames,ISNUMBER(SEARCH('Loan Due Import'!$B238,EmployeeNames)),EmployeeNames)) -> ABAD, FLORIDA RAMOS | IA2: =IF('Loan Due Import'!$B239="",EmployeeNames,_xlfn._xlws.FILTER(EmployeeNames,ISNUMBER(SEARCH('Loan Due Import'!$B239,EmployeeNames)),EmployeeNames)) -> ABAD, FLORIDA RAMOS | IB2: =IF('Loan Due Import'!$B240="",EmployeeNames,_xlfn._xlws.FILTER(EmployeeNames,ISNUMBER(SEARCH('Loan Due Import'!$B240,EmployeeNames)),EmployeeNames)) -> ABAD, FLORIDA RAMOS | IC2: =IF('Loan Due Import'!$B241="",EmployeeNames,_xlfn._xlws.FILTER(EmployeeNames,ISNUMBER(SEARCH('Loan Due Import'!$B241,EmployeeNames)),EmployeeNames)) -> ABAD, FLORIDA RAMOS | ID2: =IF('Loan Due Import'!$B242="",EmployeeNames,_xlfn._xlws.FILTER(EmployeeNames,ISNUMBER(SEARCH('Loan Due Import'!$B242,EmployeeNames)),EmployeeNames)) -> ABAD, FLORIDA RAMOS | IE2: =IF('Loan Due Import'!$B243="",EmployeeNames,_xlfn._xlws.FILTER(EmployeeNames,ISNUMBER(SEARCH('Loan Due Import'!$B243,EmployeeNames)),EmployeeNames)) -> ABAD, FLORIDA RAMOS | IF2: =IF('Loan Due Import'!$B244="",EmployeeNames,_xlfn._xlws.FILTER(EmployeeNames,ISNUMBER(SEARCH('Loan Due Import'!$B244,EmployeeNames)),EmployeeNames)) -> ABAD, FLORIDA RAMOS | IG2: =IF('Loan Due Import'!$B245="",EmployeeNames,_xlfn._xlws.FILTER(EmployeeNames,ISNUMBER(SEARCH('Loan Due Import'!$B245,EmployeeNames)),EmployeeNames)) -> ABAD, FLORIDA RAMOS | IH2: =IF('Loan Due Import'!$B246="",EmployeeNames,_xlfn._xlws.FILTER(EmployeeNames,ISNUMBER(SEARCH('Loan Due Import'!$B246,EmployeeNames)),EmployeeNames)) -> ABAD, FLORIDA RAMOS | II2: =IF('Loan Due Import'!$B247="",EmployeeNames,_xlfn._xlws.FILTER(EmployeeNames,ISNUMBER(SEARCH('Loan Due Import'!$B247,EmployeeNames)),EmployeeNames)) -> ABAD, FLORIDA RAMOS | IJ2: =IF('Loan Due Import'!$B248="",EmployeeNames,_xlfn._xlws.FILTER(EmployeeNames,ISNUMBER(SEARCH('Loan Due Import'!$B248,EmployeeNames)),EmployeeNames)) -> ABAD, FLORIDA RAMOS | IK2: =IF('Loan Due Import'!$B249="",EmployeeNames,_xlfn._xlws.FILTER(EmployeeNames,ISNUMBER(SEARCH('Loan Due Import'!$B249,EmployeeNames)),EmployeeNames)) -> ABAD, FLORIDA RAMOS | IL2: =IF('Loan Due Import'!$B250="",EmployeeNames,_xlfn._xlws.FILTER(EmployeeNames,ISNUMBER(SEARCH('Loan Due Import'!$B250,EmployeeNames)),EmployeeNames)) -> ABAD, FLORIDA RAMOS | IM2: =IF('Loan Due Import'!$B251="",EmployeeNames,_xlfn._xlws.FILTER(EmployeeNames,ISNUMBER(SEARCH('Loan Due Import'!$B251,EmployeeNames)),EmployeeNames)) -> ABAD, FLORIDA RAMOS | IN2: =IF('Loan Due Import'!$B252="",EmployeeNames,_xlfn._xlws.FILTER(EmployeeNames,ISNUMBER(SEARCH('Loan Due Import'!$B252,EmployeeNames)),EmployeeNames)) -> ABAD, FLORIDA RAMOS | IO2: =IF('Loan Due Import'!$B253="",EmployeeNames,_xlfn._xlws.FILTER(EmployeeNames,ISNUMBER(SEARCH('Loan Due Import'!$B253,EmployeeNames)),EmployeeNames)) -> ABAD, FLORIDA RAMOS | IP2: =IF('Loan Due Import'!$B254="",EmployeeNames,_xlfn._xlws.FILTER(EmployeeNames,ISNUMBER(SEARCH('Loan Due Import'!$B254,EmployeeNames)),EmployeeNames)) -> ABAD, FLORIDA RAMOS | IQ2: =IF('Loan Due Import'!$B255="",EmployeeNames,_xlfn._xlws.FILTER(EmployeeNames,ISNUMBER(SEARCH('Loan Due Import'!$B255,EmployeeNames)),EmployeeNames)) -> ABAD, FLORIDA RAMOS | IR2: =IF('Loan Due Import'!$B256="",EmployeeNames,_xlfn._xlws.FILTER(EmployeeNames,ISNUMBER(SEARCH('Loan Due Import'!$B256,EmployeeNames)),EmployeeNames)) -> ABAD, FLORIDA RAMOS | IS2: =IF('Loan Due Import'!$B257="",EmployeeNames,_xlfn._xlws.FILTER(EmployeeNames,ISNUMBER(SEARCH('Loan Due Import'!$B257,EmployeeNames)),EmployeeNames)) -> ABAD, FLORIDA RAMOS | IT2: =IF('Loan Due Import'!$B258="",EmployeeNames,_xlfn._xlws.FILTER(EmployeeNames,ISNUMBER(SEARCH('Loan Due Import'!$B258,EmployeeNames)),EmployeeNames)) -> ABAD, FLORIDA RAMOS | IU2: =IF('Loan Due Import'!$B259="",EmployeeNames,_xlfn._xlws.FILTER(EmployeeNames,ISNUMBER(SEARCH('Loan Due Import'!$B259,EmployeeNames)),EmployeeNames)) -> ABAD, FLORIDA RAMOS | IV2: =IF('Loan Due Import'!$B260="",EmployeeNames,_xlfn._xlws.FILTER(EmployeeNames,ISNUMBER(SEARCH('Loan Due Import'!$B260,EmployeeNames)),EmployeeNames)) -> ABAD, FLORIDA RAMOS | IW2: =IF('Loan Due Import'!$B261="",EmployeeNames,_xlfn._xlws.FILTER(EmployeeNames,ISNUMBER(SEARCH('Loan Due Import'!$B261,EmployeeNames)),EmployeeNames)) -> ABAD, FLORIDA RAMOS | IX2: =IF('Loan Due Import'!$B262="",EmployeeNames,_xlfn._xlws.FILTER(EmployeeNames,ISNUMBER(SEARCH('Loan Due Import'!$B262,EmployeeNames)),EmployeeNames)) -> ABAD, FLORIDA RAMOS | IY2: =IF('Loan Due Import'!$B263="",EmployeeNames,_xlfn._xlws.FILTER(EmployeeNames,ISNUMBER(SEARCH('Loan Due Import'!$B263,EmployeeNames)),EmployeeNames)) -> ABAD, FLORIDA RAMOS | IZ2: =IF('Loan Due Import'!$B264="",EmployeeNames,_xlfn._xlws.FILTER(EmployeeNames,ISNUMBER(SEARCH('Loan Due Import'!$B264,EmployeeNames)),EmployeeNames)) -> ABAD, FLORIDA RAMOS | JA2: =IF('Loan Due Import'!$B265="",EmployeeNames,_xlfn._xlws.FILTER(EmployeeNames,ISNUMBER(SEARCH('Loan Due Import'!$B265,EmployeeNames)),EmployeeNames)) -> ABAD, FLORIDA RAMOS | JB2: =IF('Loan Due Import'!$B266="",EmployeeNames,_xlfn._xlws.FILTER(EmployeeNames,ISNUMBER(SEARCH('Loan Due Import'!$B266,EmployeeNames)),EmployeeNames)) -> ABAD, FLORIDA RAMOS | JC2: =IF('Loan Due Import'!$B267="",EmployeeNames,_xlfn._xlws.FILTER(EmployeeNames,ISNUMBER(SEARCH('Loan Due Import'!$B267,EmployeeNames)),EmployeeNames)) -> ABAD, FLORIDA RAMOS | JD2: =IF('Loan Due Import'!$B268="",EmployeeNames,_xlfn._xlws.FILTER(EmployeeNames,ISNUMBER(SEARCH('Loan Due Import'!$B268,EmployeeNames)),EmployeeNames)) -> ABAD, FLORIDA RAMOS | JE2: =IF('Loan Due Import'!$B269="",EmployeeNames,_xlfn._xlws.FILTER(EmployeeNames,ISNUMBER(SEARCH('Loan Due Import'!$B269,EmployeeNames)),EmployeeNames)) -> ABAD, FLORIDA RAMOS | JF2: =IF('Loan Due Import'!$B270="",EmployeeNames,_xlfn._xlws.FILTER(EmployeeNames,ISNUMBER(SEARCH('Loan Due Import'!$B270,EmployeeNames)),EmployeeNames)) -> ABAD, FLORIDA RAMOS | JG2: =IF('Loan Due Import'!$B271="",EmployeeNames,_xlfn._xlws.FILTER(EmployeeNames,ISNUMBER(SEARCH('Loan Due Import'!$B271,EmployeeNames)),EmployeeNames)) -> ABAD, FLORIDA RAMOS | JH2: =IF('Loan Due Import'!$B272="",EmployeeNames,_xlfn._xlws.FILTER(EmployeeNames,ISNUMBER(SEARCH('Loan Due Import'!$B272,EmployeeNames)),EmployeeNames)) -> ABAD, FLORIDA RAMOS | JI2: =IF('Loan Due Import'!$B273="",EmployeeNames,_xlfn._xlws.FILTER(EmployeeNames,ISNUMBER(SEARCH('Loan Due Import'!$B273,EmployeeNames)),EmployeeNames)) -> ABAD, FLORIDA RAMOS | JJ2: =IF('Loan Due Import'!$B274="",EmployeeNames,_xlfn._xlws.FILTER(EmployeeNames,ISNUMBER(SEARCH('Loan Due Import'!$B274,EmployeeNames)),EmployeeNames)) -> ABAD, FLORIDA RAMOS | JK2: =IF('Loan Due Import'!$B275="",EmployeeNames,_xlfn._xlws.FILTER(EmployeeNames,ISNUMBER(SEARCH('Loan Due Import'!$B275,EmployeeNames)),EmployeeNames)) -> ABAD, FLORIDA RAMOS | JL2: =IF('Loan Due Import'!$B276="",EmployeeNames,_xlfn._xlws.FILTER(EmployeeNames,ISNUMBER(SEARCH('Loan Due Import'!$B276,EmployeeNames)),EmployeeNames)) -> ABAD, FLORIDA RAMOS | JM2: =IF('Loan Due Import'!$B277="",EmployeeNames,_xlfn._xlws.FILTER(EmployeeNames,ISNUMBER(SEARCH('Loan Due Import'!$B277,EmployeeNames)),EmployeeNames)) -> ABAD, FLORIDA RAMOS | JN2: =IF('Loan Due Import'!$B278="",EmployeeNames,_xlfn._xlws.FILTER(EmployeeNames,ISNUMBER(SEARCH('Loan Due Import'!$B278,EmployeeNames)),EmployeeNames)) -> ABAD, FLORIDA RAMOS | JO2: =IF('Loan Due Import'!$B279="",EmployeeNames,_xlfn._xlws.FILTER(EmployeeNames,ISNUMBER(SEARCH('Loan Due Import'!$B279,EmployeeNames)),EmployeeNames)) -> ABAD, FLORIDA RAMOS | JP2: =IF('Loan Due Import'!$B280="",EmployeeNames,_xlfn._xlws.FILTER(EmployeeNames,ISNUMBER(SEARCH('Loan Due Import'!$B280,EmployeeNames)),EmployeeNames)) -> ABAD, FLORIDA RAMOS | JQ2: =IF('Loan Due Import'!$B281="",EmployeeNames,_xlfn._xlws.FILTER(EmployeeNames,ISNUMBER(SEARCH('Loan Due Import'!$B281,EmployeeNames)),EmployeeNames)) -> ABAD, FLORIDA RAMOS | JR2: =IF('Loan Due Import'!$B282="",EmployeeNames,_xlfn._xlws.FILTER(EmployeeNames,ISNUMBER(SEARCH('Loan Due Import'!$B282,EmployeeNames)),EmployeeNames)) -> ABAD, FLORIDA RAMOS | JS2: =IF('Loan Due Import'!$B283="",EmployeeNames,_xlfn._xlws.FILTER(EmployeeNames,ISNUMBER(SEARCH('Loan Due Import'!$B283,EmployeeNames)),EmployeeNames)) -> ABAD, FLORIDA RAMOS | JT2: =IF('Loan Due Import'!$B284="",EmployeeNames,_xlfn._xlws.FILTER(EmployeeNames,ISNUMBER(SEARCH('Loan Due Import'!$B284,EmployeeNames)),EmployeeNames)) -> ABAD, FLORIDA RAMOS | JU2: =IF('Loan Due Import'!$B285="",EmployeeNames,_xlfn._xlws.FILTER(EmployeeNames,ISNUMBER(SEARCH('Loan Due Import'!$B285,EmployeeNames)),EmployeeNames)) -> ABAD, FLORIDA RAMOS | JV2: =IF('Loan Due Import'!$B286="",EmployeeNames,_xlfn._xlws.FILTER(EmployeeNames,ISNUMBER(SEARCH('Loan Due Import'!$B286,EmployeeNames)),EmployeeNames)) -> ABAD, FLORIDA RAMOS | JW2: =IF('Loan Due Import'!$B287="",EmployeeNames,_xlfn._xlws.FILTER(EmployeeNames,ISNUMBER(SEARCH('Loan Due Import'!$B287,EmployeeNames)),EmployeeNames)) -> ABAD, FLORIDA RAMOS | JX2: =IF('Loan Due Import'!$B288="",EmployeeNames,_xlfn._xlws.FILTER(EmployeeNames,ISNUMBER(SEARCH('Loan Due Import'!$B288,EmployeeNames)),EmployeeNames)) -> ABAD, FLORIDA RAMOS | JY2: =IF('Loan Due Import'!$B289="",EmployeeNames,_xlfn._xlws.FILTER(EmployeeNames,ISNUMBER(SEARCH('Loan Due Import'!$B289,EmployeeNames)),EmployeeNames)) -> ABAD, FLORIDA RAMOS | JZ2: =IF('Loan Due Import'!$B290="",EmployeeNames,_xlfn._xlws.FILTER(EmployeeNames,ISNUMBER(SEARCH('Loan Due Import'!$B290,EmployeeNames)),EmployeeNames)) -> ABAD, FLORIDA RAMOS | KA2: =IF('Loan Due Import'!$B291="",EmployeeNames,_xlfn._xlws.FILTER(EmployeeNames,ISNUMBER(SEARCH('Loan Due Import'!$B291,EmployeeNames)),EmployeeNames)) -> ABAD, FLORIDA RAMOS | KB2: =IF('Loan Due Import'!$B292="",EmployeeNames,_xlfn._xlws.FILTER(EmployeeNames,ISNUMBER(SEARCH('Loan Due Import'!$B292,EmployeeNames)),EmployeeNames)) -> ABAD, FLORIDA RAMOS | KC2: =IF('Loan Due Import'!$B293="",EmployeeNames,_xlfn._xlws.FILTER(EmployeeNames,ISNUMBER(SEARCH('Loan Due Import'!$B293,EmployeeNames)),EmployeeNames)) -> ABAD, FLORIDA RAMOS | KD2: =IF('Loan Due Import'!$B294="",EmployeeNames,_xlfn._xlws.FILTER(EmployeeNames,ISNUMBER(SEARCH('Loan Due Import'!$B294,EmployeeNames)),EmployeeNames)) -> ABAD, FLORIDA RAMOS | KE2: =IF('Loan Due Import'!$B295="",EmployeeNames,_xlfn._xlws.FILTER(EmployeeNames,ISNUMBER(SEARCH('Loan Due Import'!$B295,EmployeeNames)),EmployeeNames)) -> ABAD, FLORIDA RAMOS | KF2: =IF('Loan Due Import'!$B296="",EmployeeNames,_xlfn._xlws.FILTER(EmployeeNames,ISNUMBER(SEARCH('Loan Due Import'!$B296,EmployeeNames)),EmployeeNames)) -> ABAD, FLORIDA RAMOS | KG2: =IF('Loan Due Import'!$B297="",EmployeeNames,_xlfn._xlws.FILTER(EmployeeNames,ISNUMBER(SEARCH('Loan Due Import'!$B297,EmployeeNames)),EmployeeNames)) -> ABAD, FLORIDA RAMOS | KH2: =IF('Loan Due Import'!$B298="",EmployeeNames,_xlfn._xlws.FILTER(EmployeeNames,ISNUMBER(SEARCH('Loan Due Import'!$B298,EmployeeNames)),EmployeeNames)) -> ABAD, FLORIDA RAMOS | KI2: =IF('Loan Due Import'!$B299="",EmployeeNames,_xlfn._xlws.FILTER(EmployeeNames,ISNUMBER(SEARCH('Loan Due Import'!$B299,EmployeeNames)),EmployeeNames)) -> ABAD, FLORIDA RAMOS | KJ2: =IF('Loan Due Import'!$B300="",EmployeeNames,_xlfn._xlws.FILTER(EmployeeNames,ISNUMBER(SEARCH('Loan Due Import'!$B300,EmployeeNames)),EmployeeNames)) -> ABAD, FLORIDA RAMOS | KK2: =IF('Loan Due Import'!$B301="",EmployeeNames,_xlfn._xlws.FILTER(EmployeeNames,ISNUMBER(SEARCH('Loan Due Import'!$B301,EmployeeNames)),EmployeeNames)) -> ABAD, FLORIDA RAMOS | KL2: =IF('Loan Due Import'!$B302="",EmployeeNames,_xlfn._xlws.FILTER(EmployeeNames,ISNUMBER(SEARCH('Loan Due Import'!$B302,EmployeeNames)),EmployeeNames)) -> ABAD, FLORIDA RAMOS | KM2: =IF('Loan Due Import'!$B303="",EmployeeNames,_xlfn._xlws.FILTER(EmployeeNames,ISNUMBER(SEARCH('Loan Due Import'!$B303,EmployeeNames)),EmployeeNames)) -> ABAD, FLORIDA RAMOS | KN2: =IF('Loan Due Import'!$B304="",EmployeeNames,_xlfn._xlws.FILTER(EmployeeNames,ISNUMBER(SEARCH('Loan Due Import'!$B304,EmployeeNames)),EmployeeNames)) -> ABAD, FLORIDA RAMOS | KO2: =IF('Loan Due Import'!$B305="",EmployeeNames,_xlfn._xlws.FILTER(EmployeeNames,ISNUMBER(SEARCH('Loan Due Import'!$B305,EmployeeNames)),EmployeeNames)) -> ABAD, FLORIDA RAMOS | KP2: =IF('Loan Due Import'!$B306="",EmployeeNames,_xlfn._xlws.FILTER(EmployeeNames,ISNUMBER(SEARCH('Loan Due Import'!$B306,EmployeeNames)),EmployeeNames)) -> ABAD, FLORIDA RAMOS | KQ2: =IF('Loan Due Import'!$B307="",EmployeeNames,_xlfn._xlws.FILTER(EmployeeNames,ISNUMBER(SEARCH('Loan Due Import'!$B307,EmployeeNames)),EmployeeNames)) -> ABAD, FLORIDA RAMOS | KR2: =IF('Loan Due Import'!$B308="",EmployeeNames,_xlfn._xlws.FILTER(EmployeeNames,ISNUMBER(SEARCH('Loan Due Import'!$B308,EmployeeNames)),EmployeeNames)) -> ABAD, FLORIDA RAMOS | KS2: =IF('Loan Due Import'!$B309="",EmployeeNames,_xlfn._xlws.FILTER(EmployeeNames,ISNUMBER(SEARCH('Loan Due Import'!$B309,EmployeeNames)),EmployeeNames)) -> ABAD, FLORIDA RAMOS | KT2: =IF('Loan Due Import'!$B310="",EmployeeNames,_xlfn._xlws.FILTER(EmployeeNames,ISNUMBER(SEARCH('Loan Due Import'!$B310,EmployeeNames)),EmployeeNames)) -> ABAD, FLORIDA RAMOS | KU2: =IF('Loan Due Import'!$B311="",EmployeeNames,_xlfn._xlws.FILTER(EmployeeNames,ISNUMBER(SEARCH('Loan Due Import'!$B311,EmployeeNames)),EmployeeNames)) -> ABAD, FLORIDA RAMOS | KV2: =IF('Loan Due Import'!$B312="",EmployeeNames,_xlfn._xlws.FILTER(EmployeeNames,ISNUMBER(SEARCH('Loan Due Import'!$B312,EmployeeNames)),EmployeeNames)) -> ABAD, FLORIDA RAMOS | KW2: =IF('Loan Due Import'!$B313="",EmployeeNames,_xlfn._xlws.FILTER(EmployeeNames,ISNUMBER(SEARCH('Loan Due Import'!$B313,EmployeeNames)),EmployeeNames)) -> ABAD, FLORIDA RAMOS | KX2: =IF('Loan Due Import'!$B314="",EmployeeNames,_xlfn._xlws.FILTER(EmployeeNames,ISNUMBER(SEARCH('Loan Due Import'!$B314,EmployeeNames)),EmployeeNames)) -> ABAD, FLORIDA RAMOS | KY2: =IF('Loan Due Import'!$B315="",EmployeeNames,_xlfn._xlws.FILTER(EmployeeNames,ISNUMBER(SEARCH('Loan Due Import'!$B315,EmployeeNames)),EmployeeNames)) -> ABAD, FLORIDA RAMOS | KZ2: =IF('Loan Due Import'!$B316="",EmployeeNames,_xlfn._xlws.FILTER(EmployeeNames,ISNUMBER(SEARCH('Loan Due Import'!$B316,EmployeeNames)),EmployeeNames)) -> ABAD, FLORIDA RAMOS | LA2: =IF('Loan Due Import'!$B317="",EmployeeNames,_xlfn._xlws.FILTER(EmployeeNames,ISNUMBER(SEARCH('Loan Due Import'!$B317,EmployeeNames)),EmployeeNames)) -> ABAD, FLORIDA RAMOS | LB2: =IF('Loan Due Import'!$B318="",EmployeeNames,_xlfn._xlws.FILTER(EmployeeNames,ISNUMBER(SEARCH('Loan Due Import'!$B318,EmployeeNames)),EmployeeNames)) -> ABAD, FLORIDA RAMOS | LC2: =IF('Loan Due Import'!$B319="",EmployeeNames,_xlfn._xlws.FILTER(EmployeeNames,ISNUMBER(SEARCH('Loan Due Import'!$B319,EmployeeNames)),EmployeeNames)) -> ABAD, FLORIDA RAMOS | LD2: =IF('Loan Due Import'!$B320="",EmployeeNames,_xlfn._xlws.FILTER(EmployeeNames,ISNUMBER(SEARCH('Loan Due Import'!$B320,EmployeeNames)),EmployeeNames)) -> ABAD, FLORIDA RAMOS | LE2: =IF('Loan Due Import'!$B321="",EmployeeNames,_xlfn._xlws.FILTER(EmployeeNames,ISNUMBER(SEARCH('Loan Due Import'!$B321,EmployeeNames)),EmployeeNames)) -> ABAD, FLORIDA RAMOS | LF2: =IF('Loan Due Import'!$B322="",EmployeeNames,_xlfn._xlws.FILTER(EmployeeNames,ISNUMBER(SEARCH('Loan Due Import'!$B322,EmployeeNames)),EmployeeNames)) -> ABAD, FLORIDA RAMOS | LG2: =IF('Loan Due Import'!$B323="",EmployeeNames,_xlfn._xlws.FILTER(EmployeeNames,ISNUMBER(SEARCH('Loan Due Import'!$B323,EmployeeNames)),EmployeeNames)) -> ABAD, FLORIDA RAMOS | LH2: =IF('Loan Due Import'!$B324="",EmployeeNames,_xlfn._xlws.FILTER(EmployeeNames,ISNUMBER(SEARCH('Loan Due Import'!$B324,EmployeeNames)),EmployeeNames)) -> ABAD, FLORIDA RAMOS | LI2: =IF('Loan Due Import'!$B325="",EmployeeNames,_xlfn._xlws.FILTER(EmployeeNames,ISNUMBER(SEARCH('Loan Due Import'!$B325,EmployeeNames)),EmployeeNames)) -> ABAD, FLORIDA RAMOS | LJ2: =IF('Loan Due Import'!$B326="",EmployeeNames,_xlfn._xlws.FILTER(EmployeeNames,ISNUMBER(SEARCH('Loan Due Import'!$B326,EmployeeNames)),EmployeeNames)) -> ABAD, FLORIDA RAMOS | LK2: =IF('Loan Due Import'!$B327="",EmployeeNames,_xlfn._xlws.FILTER(EmployeeNames,ISNUMBER(SEARCH('Loan Due Import'!$B327,EmployeeNames)),EmployeeNames)) -> ABAD, FLORIDA RAMOS | LL2: =IF('Loan Due Import'!$B328="",EmployeeNames,_xlfn._xlws.FILTER(EmployeeNames,ISNUMBER(SEARCH('Loan Due Import'!$B328,EmployeeNames)),EmployeeNames)) -> ABAD, FLORIDA RAMOS | LM2: =IF('Loan Due Import'!$B329="",EmployeeNames,_xlfn._xlws.FILTER(EmployeeNames,ISNUMBER(SEARCH('Loan Due Import'!$B329,EmployeeNames)),EmployeeNames)) -> ABAD, FLORIDA RAMOS | LN2: =IF('Loan Due Import'!$B330="",EmployeeNames,_xlfn._xlws.FILTER(EmployeeNames,ISNUMBER(SEARCH('Loan Due Import'!$B330,EmployeeNames)),EmployeeNames)) -> ABAD, FLORIDA RAMOS | LO2: =IF('Loan Due Import'!$B331="",EmployeeNames,_xlfn._xlws.FILTER(EmployeeNames,ISNUMBER(SEARCH('Loan Due Import'!$B331,EmployeeNames)),EmployeeNames)) -> ABAD, FLORIDA RAMOS | LP2: =IF('Loan Due Import'!$B332="",EmployeeNames,_xlfn._xlws.FILTER(EmployeeNames,ISNUMBER(SEARCH('Loan Due Import'!$B332,EmployeeNames)),EmployeeNames)) -> ABAD, FLORIDA RAMOS | LQ2: =IF('Loan Due Import'!$B333="",EmployeeNames,_xlfn._xlws.FILTER(EmployeeNames,ISNUMBER(SEARCH('Loan Due Import'!$B333,EmployeeNames)),EmployeeNames)) -> ABAD, FLORIDA RAMOS | LR2: =IF('Loan Due Import'!$B334="",EmployeeNames,_xlfn._xlws.FILTER(EmployeeNames,ISNUMBER(SEARCH('Loan Due Import'!$B334,EmployeeNames)),EmployeeNames)) -> ABAD, FLORIDA RAMOS | LS2: =IF('Loan Due Import'!$B335="",EmployeeNames,_xlfn._xlws.FILTER(EmployeeNames,ISNUMBER(SEARCH('Loan Due Import'!$B335,EmployeeNames)),EmployeeNames)) -> ABAD, FLORIDA RAMOS | LT2: =IF('Loan Due Import'!$B336="",EmployeeNames,_xlfn._xlws.FILTER(EmployeeNames,ISNUMBER(SEARCH('Loan Due Import'!$B336,EmployeeNames)),EmployeeNames)) -> ABAD, FLORIDA RAMOS | LU2: =IF('Loan Due Import'!$B337="",EmployeeNames,_xlfn._xlws.FILTER(EmployeeNames,ISNUMBER(SEARCH('Loan Due Import'!$B337,EmployeeNames)),EmployeeNames)) -> ABAD, FLORIDA RAMOS | LV2: =IF('Loan Due Import'!$B338="",EmployeeNames,_xlfn._xlws.FILTER(EmployeeNames,ISNUMBER(SEARCH('Loan Due Import'!$B338,EmployeeNames)),EmployeeNames)) -> ABAD, FLORIDA RAMOS | LW2: =IF('Loan Due Import'!$B339="",EmployeeNames,_xlfn._xlws.FILTER(EmployeeNames,ISNUMBER(SEARCH('Loan Due Import'!$B339,EmployeeNames)),EmployeeNames)) -> ABAD, FLORIDA RAMOS | LX2: =IF('Loan Due Import'!$B340="",EmployeeNames,_xlfn._xlws.FILTER(EmployeeNames,ISNUMBER(SEARCH('Loan Due Import'!$B340,EmployeeNames)),EmployeeNames)) -> ABAD, FLORIDA RAMOS | LY2: =IF('Loan Due Import'!$B341="",EmployeeNames,_xlfn._xlws.FILTER(EmployeeNames,ISNUMBER(SEARCH('Loan Due Import'!$B341,EmployeeNames)),EmployeeNames)) -> ABAD, FLORIDA RAMOS | LZ2: =IF('Loan Due Import'!$B342="",EmployeeNames,_xlfn._xlws.FILTER(EmployeeNames,ISNUMBER(SEARCH('Loan Due Import'!$B342,EmployeeNames)),EmployeeNames)) -> ABAD, FLORIDA RAMOS | MA2: =IF('Loan Due Import'!$B343="",EmployeeNames,_xlfn._xlws.FILTER(EmployeeNames,ISNUMBER(SEARCH('Loan Due Import'!$B343,EmployeeNames)),EmployeeNames)) -> ABAD, FLORIDA RAMOS | MB2: =IF('Loan Due Import'!$B344="",EmployeeNames,_xlfn._xlws.FILTER(EmployeeNames,ISNUMBER(SEARCH('Loan Due Import'!$B344,EmployeeNames)),EmployeeNames)) -> ABAD, FLORIDA RAMOS | MC2: =IF('Loan Due Import'!$B345="",EmployeeNames,_xlfn._xlws.FILTER(EmployeeNames,ISNUMBER(SEARCH('Loan Due Import'!$B345,EmployeeNames)),EmployeeNames)) -> ABAD, FLORIDA RAMOS | MD2: =IF('Loan Due Import'!$B346="",EmployeeNames,_xlfn._xlws.FILTER(EmployeeNames,ISNUMBER(SEARCH('Loan Due Import'!$B346,EmployeeNames)),EmployeeNames)) -> ABAD, FLORIDA RAMOS | ME2: =IF('Loan Due Import'!$B347="",EmployeeNames,_xlfn._xlws.FILTER(EmployeeNames,ISNUMBER(SEARCH('Loan Due Import'!$B347,EmployeeNames)),EmployeeNames)) -> ABAD, FLORIDA RAMOS | MF2: =IF('Loan Due Import'!$B348="",EmployeeNames,_xlfn._xlws.FILTER(EmployeeNames,ISNUMBER(SEARCH('Loan Due Import'!$B348,EmployeeNames)),EmployeeNames)) -> ABAD, FLORIDA RAMOS | MG2: =IF('Loan Due Import'!$B349="",EmployeeNames,_xlfn._xlws.FILTER(EmployeeNames,ISNUMBER(SEARCH('Loan Due Import'!$B349,EmployeeNames)),EmployeeNames)) -> ABAD, FLORIDA RAMOS | MH2: =IF('Loan Due Import'!$B350="",EmployeeNames,_xlfn._xlws.FILTER(EmployeeNames,ISNUMBER(SEARCH('Loan Due Import'!$B350,EmployeeNames)),EmployeeNames)) -> ABAD, FLORIDA RAMOS | MI2: =IF('Loan Due Import'!$B351="",EmployeeNames,_xlfn._xlws.FILTER(EmployeeNames,ISNUMBER(SEARCH('Loan Due Import'!$B351,EmployeeNames)),EmployeeNames)) -> ABAD, FLORIDA RAMOS | MJ2: =IF('Loan Due Import'!$B352="",EmployeeNames,_xlfn._xlws.FILTER(EmployeeNames,ISNUMBER(SEARCH('Loan Due Import'!$B352,EmployeeNames)),EmployeeNames)) -> ABAD, FLORIDA RAMOS | MK2: =IF('Loan Due Import'!$B353="",EmployeeNames,_xlfn._xlws.FILTER(EmployeeNames,ISNUMBER(SEARCH('Loan Due Import'!$B353,EmployeeNames)),EmployeeNames)) -> ABAD, FLORIDA RAMOS | ML2: =IF('Loan Due Import'!$B354="",EmployeeNames,_xlfn._xlws.FILTER(EmployeeNames,ISNUMBER(SEARCH('Loan Due Import'!$B354,EmployeeNames)),EmployeeNames)) -> ABAD, FLORIDA RAMOS | MM2: =IF('Loan Due Import'!$B355="",EmployeeNames,_xlfn._xlws.FILTER(EmployeeNames,ISNUMBER(SEARCH('Loan Due Import'!$B355,EmployeeNames)),EmployeeNames)) -> ABAD, FLORIDA RAMOS | MN2: =IF('Loan Due Import'!$B356="",EmployeeNames,_xlfn._xlws.FILTER(EmployeeNames,ISNUMBER(SEARCH('Loan Due Import'!$B356,EmployeeNames)),EmployeeNames)) -> ABAD, FLORIDA RAMOS | MO2: =IF('Loan Due Import'!$B357="",EmployeeNames,_xlfn._xlws.FILTER(EmployeeNames,ISNUMBER(SEARCH('Loan Due Import'!$B357,EmployeeNames)),EmployeeNames)) -> ABAD, FLORIDA RAMOS | MP2: =IF('Loan Due Import'!$B358="",EmployeeNames,_xlfn._xlws.FILTER(EmployeeNames,ISNUMBER(SEARCH('Loan Due Import'!$B358,EmployeeNames)),EmployeeNames)) -> ABAD, FLORIDA RAMOS | MQ2: =IF('Loan Due Import'!$B359="",EmployeeNames,_xlfn._xlws.FILTER(EmployeeNames,ISNUMBER(SEARCH('Loan Due Import'!$B359,EmployeeNames)),EmployeeNames)) -> ABAD, FLORIDA RAMOS | MR2: =IF('Loan Due Import'!$B360="",EmployeeNames,_xlfn._xlws.FILTER(EmployeeNames,ISNUMBER(SEARCH('Loan Due Import'!$B360,EmployeeNames)),EmployeeNames)) -> ABAD, FLORIDA RAMOS | MS2: =IF('Loan Due Import'!$B361="",EmployeeNames,_xlfn._xlws.FILTER(EmployeeNames,ISNUMBER(SEARCH('Loan Due Import'!$B361,EmployeeNames)),EmployeeNames)) -> ABAD, FLORIDA RAMOS | MT2: =IF('Loan Due Import'!$B362="",EmployeeNames,_xlfn._xlws.FILTER(EmployeeNames,ISNUMBER(SEARCH('Loan Due Import'!$B362,EmployeeNames)),EmployeeNames)) -> ABAD, FLORIDA RAMOS | MU2: =IF('Loan Due Import'!$B363="",EmployeeNames,_xlfn._xlws.FILTER(EmployeeNames,ISNUMBER(SEARCH('Loan Due Import'!$B363,EmployeeNames)),EmployeeNames)) -> ABAD, FLORIDA RAMOS | MV2: =IF('Loan Due Import'!$B364="",EmployeeNames,_xlfn._xlws.FILTER(EmployeeNames,ISNUMBER(SEARCH('Loan Due Import'!$B364,EmployeeNames)),EmployeeNames)) -> ABAD, FLORIDA RAMOS | MW2: =IF('Loan Due Import'!$B365="",EmployeeNames,_xlfn._xlws.FILTER(EmployeeNames,ISNUMBER(SEARCH('Loan Due Import'!$B365,EmployeeNames)),EmployeeNames)) -> ABAD, FLORIDA RAMOS | MX2: =IF('Loan Due Import'!$B366="",EmployeeNames,_xlfn._xlws.FILTER(EmployeeNames,ISNUMBER(SEARCH('Loan Due Import'!$B366,EmployeeNames)),EmployeeNames)) -> ABAD, FLORIDA RAMOS | MY2: =IF('Loan Due Import'!$B367="",EmployeeNames,_xlfn._xlws.FILTER(EmployeeNames,ISNUMBER(SEARCH('Loan Due Import'!$B367,EmployeeNames)),EmployeeNames)) -> ABAD, FLORIDA RAMOS | MZ2: =IF('Loan Due Import'!$B368="",EmployeeNames,_xlfn._xlws.FILTER(EmployeeNames,ISNUMBER(SEARCH('Loan Due Import'!$B368,EmployeeNames)),EmployeeNames)) -> ABAD, FLORIDA RAMOS | NA2: =IF('Loan Due Import'!$B369="",EmployeeNames,_xlfn._xlws.FILTER(EmployeeNames,ISNUMBER(SEARCH('Loan Due Import'!$B369,EmployeeNames)),EmployeeNames)) -> ABAD, FLORIDA RAMOS | NB2: =IF('Loan Due Import'!$B370="",EmployeeNames,_xlfn._xlws.FILTER(EmployeeNames,ISNUMBER(SEARCH('Loan Due Import'!$B370,EmployeeNames)),EmployeeNames)) -> ABAD, FLORIDA RAMOS | NC2: =IF('Loan Due Import'!$B371="",EmployeeNames,_xlfn._xlws.FILTER(EmployeeNames,ISNUMBER(SEARCH('Loan Due Import'!$B371,EmployeeNames)),EmployeeNames)) -> ABAD, FLORIDA RAMOS | ND2: =IF('Loan Due Import'!$B372="",EmployeeNames,_xlfn._xlws.FILTER(EmployeeNames,ISNUMBER(SEARCH('Loan Due Import'!$B372,EmployeeNames)),EmployeeNames)) -> ABAD, FLORIDA RAMOS | NE2: =IF('Loan Due Import'!$B373="",EmployeeNames,_xlfn._xlws.FILTER(EmployeeNames,ISNUMBER(SEARCH('Loan Due Import'!$B373,EmployeeNames)),EmployeeNames)) -> ABAD, FLORIDA RAMOS | NF2: =IF('Loan Due Import'!$B374="",EmployeeNames,_xlfn._xlws.FILTER(EmployeeNames,ISNUMBER(SEARCH('Loan Due Import'!$B374,EmployeeNames)),EmployeeNames)) -> ABAD, FLORIDA RAMOS | NG2: =IF('Loan Due Import'!$B375="",EmployeeNames,_xlfn._xlws.FILTER(EmployeeNames,ISNUMBER(SEARCH('Loan Due Import'!$B375,EmployeeNames)),EmployeeNames)) -> ABAD, FLORIDA RAMOS | NH2: =IF('Loan Due Import'!$B376="",EmployeeNames,_xlfn._xlws.FILTER(EmployeeNames,ISNUMBER(SEARCH('Loan Due Import'!$B376,EmployeeNames)),EmployeeNames)) -> ABAD, FLORIDA RAMOS | NI2: =IF('Loan Due Import'!$B377="",EmployeeNames,_xlfn._xlws.FILTER(EmployeeNames,ISNUMBER(SEARCH('Loan Due Import'!$B377,EmployeeNames)),EmployeeNames)) -> ABAD, FLORIDA RAMOS | NJ2: =IF('Loan Due Import'!$B378="",EmployeeNames,_xlfn._xlws.FILTER(EmployeeNames,ISNUMBER(SEARCH('Loan Due Import'!$B378,EmployeeNames)),EmployeeNames)) -> ABAD, FLORIDA RAMOS | NK2: =IF('Loan Due Import'!$B379="",EmployeeNames,_xlfn._xlws.FILTER(EmployeeNames,ISNUMBER(SEARCH('Loan Due Import'!$B379,EmployeeNames)),EmployeeNames)) -> ABAD, FLORIDA RAMOS | NL2: =IF('Loan Due Import'!$B380="",EmployeeNames,_xlfn._xlws.FILTER(EmployeeNames,ISNUMBER(SEARCH('Loan Due Import'!$B380,EmployeeNames)),EmployeeNames)) -> ABAD, FLORIDA RAMOS | NM2: =IF('Loan Due Import'!$B381="",EmployeeNames,_xlfn._xlws.FILTER(EmployeeNames,ISNUMBER(SEARCH('Loan Due Import'!$B381,EmployeeNames)),EmployeeNames)) -> ABAD, FLORIDA RAMOS | NN2: =IF('Loan Due Import'!$B382="",EmployeeNames,_xlfn._xlws.FILTER(EmployeeNames,ISNUMBER(SEARCH('Loan Due Import'!$B382,EmployeeNames)),EmployeeNames)) -> ABAD, FLORIDA RAMOS | NO2: =IF('Loan Due Import'!$B383="",EmployeeNames,_xlfn._xlws.FILTER(EmployeeNames,ISNUMBER(SEARCH('Loan Due Import'!$B383,EmployeeNames)),EmployeeNames)) -> ABAD, FLORIDA RAMOS | NP2: =IF('Loan Due Import'!$B384="",EmployeeNames,_xlfn._xlws.FILTER(EmployeeNames,ISNUMBER(SEARCH('Loan Due Import'!$B384,EmployeeNames)),EmployeeNames)) -> ABAD, FLORIDA RAMOS | NQ2: =IF('Loan Due Import'!$B385="",EmployeeNames,_xlfn._xlws.FILTER(EmployeeNames,ISNUMBER(SEARCH('Loan Due Import'!$B385,EmployeeNames)),EmployeeNames)) -> ABAD, FLORIDA RAMOS | NR2: =IF('Loan Due Import'!$B386="",EmployeeNames,_xlfn._xlws.FILTER(EmployeeNames,ISNUMBER(SEARCH('Loan Due Import'!$B386,EmployeeNames)),EmployeeNames)) -> ABAD, FLORIDA RAMOS | NS2: =IF('Loan Due Import'!$B387="",EmployeeNames,_xlfn._xlws.FILTER(EmployeeNames,ISNUMBER(SEARCH('Loan Due Import'!$B387,EmployeeNames)),EmployeeNames)) -> ABAD, FLORIDA RAMOS | NT2: =IF('Loan Due Import'!$B388="",EmployeeNames,_xlfn._xlws.FILTER(EmployeeNames,ISNUMBER(SEARCH('Loan Due Import'!$B388,EmployeeNames)),EmployeeNames)) -> ABAD, FLORIDA RAMOS | NU2: =IF('Loan Due Import'!$B389="",EmployeeNames,_xlfn._xlws.FILTER(EmployeeNames,ISNUMBER(SEARCH('Loan Due Import'!$B389,EmployeeNames)),EmployeeNames)) -> ABAD, FLORIDA RAMOS | NV2: =IF('Loan Due Import'!$B390="",EmployeeNames,_xlfn._xlws.FILTER(EmployeeNames,ISNUMBER(SEARCH('Loan Due Import'!$B390,EmployeeNames)),EmployeeNames)) -> ABAD, FLORIDA RAMOS | NW2: =IF('Loan Due Import'!$B391="",EmployeeNames,_xlfn._xlws.FILTER(EmployeeNames,ISNUMBER(SEARCH('Loan Due Import'!$B391,EmployeeNames)),EmployeeNames)) -> ABAD, FLORIDA RAMOS | NX2: =IF('Loan Due Import'!$B392="",EmployeeNames,_xlfn._xlws.FILTER(EmployeeNames,ISNUMBER(SEARCH('Loan Due Import'!$B392,EmployeeNames)),EmployeeNames)) -> ABAD, FLORIDA RAMOS | NY2: =IF('Loan Due Import'!$B393="",EmployeeNames,_xlfn._xlws.FILTER(EmployeeNames,ISNUMBER(SEARCH('Loan Due Import'!$B393,EmployeeNames)),EmployeeNames)) -> ABAD, FLORIDA RAMOS | NZ2: =IF('Loan Due Import'!$B394="",EmployeeNames,_xlfn._xlws.FILTER(EmployeeNames,ISNUMBER(SEARCH('Loan Due Import'!$B394,EmployeeNames)),EmployeeNames)) -> ABAD, FLORIDA RAMOS | OA2: =IF('Loan Due Import'!$B395="",EmployeeNames,_xlfn._xlws.FILTER(EmployeeNames,ISNUMBER(SEARCH('Loan Due Import'!$B395,EmployeeNames)),EmployeeNames)) -> ABAD, FLORIDA RAMOS | OB2: =IF('Loan Due Import'!$B396="",EmployeeNames,_xlfn._xlws.FILTER(EmployeeNames,ISNUMBER(SEARCH('Loan Due Import'!$B396,EmployeeNames)),EmployeeNames)) -> ABAD, FLORIDA RAMOS | OC2: =IF('Loan Due Import'!$B397="",EmployeeNames,_xlfn._xlws.FILTER(EmployeeNames,ISNUMBER(SEARCH('Loan Due Import'!$B397,EmployeeNames)),EmployeeNames)) -> ABAD, FLORIDA RAMOS | OD2: =IF('Loan Due Import'!$B398="",EmployeeNames,_xlfn._xlws.FILTER(EmployeeNames,ISNUMBER(SEARCH('Loan Due Import'!$B398,EmployeeNames)),EmployeeNames)) -> ABAD, FLORIDA RAMOS | OE2: =IF('Loan Due Import'!$B399="",EmployeeNames,_xlfn._xlws.FILTER(EmployeeNames,ISNUMBER(SEARCH('Loan Due Import'!$B399,EmployeeNames)),EmployeeNames)) -> ABAD, FLORIDA RAMOS | OF2: =IF('Loan Due Import'!$B400="",EmployeeNames,_xlfn._xlws.FILTER(EmployeeNames,ISNUMBER(SEARCH('Loan Due Import'!$B400,EmployeeNames)),EmployeeNames)) -> ABAD, FLORIDA RAMOS | OG2: =IF('Loan Due Import'!$B401="",EmployeeNames,_xlfn._xlws.FILTER(EmployeeNames,ISNUMBER(SEARCH('Loan Due Import'!$B401,EmployeeNames)),EmployeeNames)) -> ABAD, FLORIDA RAMOS | OH2: =IF('Loan Due Import'!$B402="",EmployeeNames,_xlfn._xlws.FILTER(EmployeeNames,ISNUMBER(SEARCH('Loan Due Import'!$B402,EmployeeNames)),EmployeeNames)) -> ABAD, FLORIDA RAMOS | OI2: =IF('Loan Due Import'!$B403="",EmployeeNames,_xlfn._xlws.FILTER(EmployeeNames,ISNUMBER(SEARCH('Loan Due Import'!$B403,EmployeeNames)),EmployeeNames)) -> ABAD, FLORIDA RAMOS | OJ2: =IF('Loan Due Import'!$B404="",EmployeeNames,_xlfn._xlws.FILTER(EmployeeNames,ISNUMBER(SEARCH('Loan Due Import'!$B404,EmployeeNames)),EmployeeNames)) -> ABAD, FLORIDA RAMOS | OK2: =IF('Loan Due Import'!$B405="",EmployeeNames,_xlfn._xlws.FILTER(EmployeeNames,ISNUMBER(SEARCH('Loan Due Import'!$B405,EmployeeNames)),EmployeeNames)) -> ABAD, FLORIDA RAMOS | OL2: =IF('Loan Due Import'!$B406="",EmployeeNames,_xlfn._xlws.FILTER(EmployeeNames,ISNUMBER(SEARCH('Loan Due Import'!$B406,EmployeeNames)),EmployeeNames)) -> ABAD, FLORIDA RAMOS | OM2: =IF('Loan Due Import'!$B407="",EmployeeNames,_xlfn._xlws.FILTER(EmployeeNames,ISNUMBER(SEARCH('Loan Due Import'!$B407,EmployeeNames)),EmployeeNames)) -> ABAD, FLORIDA RAMOS | ON2: =IF('Loan Due Import'!$B408="",EmployeeNames,_xlfn._xlws.FILTER(EmployeeNames,ISNUMBER(SEARCH('Loan Due Import'!$B408,EmployeeNames)),EmployeeNames)) -> ABAD, FLORIDA RAMOS | OO2: =IF('Loan Due Import'!$B409="",EmployeeNames,_xlfn._xlws.FILTER(EmployeeNames,ISNUMBER(SEARCH('Loan Due Import'!$B409,EmployeeNames)),EmployeeNames)) -> ABAD, FLORIDA RAMOS | OP2: =IF('Loan Due Import'!$B410="",EmployeeNames,_xlfn._xlws.FILTER(EmployeeNames,ISNUMBER(SEARCH('Loan Due Import'!$B410,EmployeeNames)),EmployeeNames)) -> ABAD, FLORIDA RAMOS | OQ2: =IF('Loan Due Import'!$B411="",EmployeeNames,_xlfn._xlws.FILTER(EmployeeNames,ISNUMBER(SEARCH('Loan Due Import'!$B411,EmployeeNames)),EmployeeNames)) -> ABAD, FLORIDA RAMOS | OR2: =IF('Loan Due Import'!$B412="",EmployeeNames,_xlfn._xlws.FILTER(EmployeeNames,ISNUMBER(SEARCH('Loan Due Import'!$B412,EmployeeNames)),EmployeeNames)) -> ABAD, FLORIDA RAMOS | OS2: =IF('Loan Due Import'!$B413="",EmployeeNames,_xlfn._xlws.FILTER(EmployeeNames,ISNUMBER(SEARCH('Loan Due Import'!$B413,EmployeeNames)),EmployeeNames)) -> ABAD, FLORIDA RAMOS | OT2: =IF('Loan Due Import'!$B414="",EmployeeNames,_xlfn._xlws.FILTER(EmployeeNames,ISNUMBER(SEARCH('Loan Due Import'!$B414,EmployeeNames)),EmployeeNames)) -> ABAD, FLORIDA RAMOS | OU2: =IF('Loan Due Import'!$B415="",EmployeeNames,_xlfn._xlws.FILTER(EmployeeNames,ISNUMBER(SEARCH('Loan Due Import'!$B415,EmployeeNames)),EmployeeNames)) -> ABAD, FLORIDA RAMOS | OV2: =IF('Loan Due Import'!$B416="",EmployeeNames,_xlfn._xlws.FILTER(EmployeeNames,ISNUMBER(SEARCH('Loan Due Import'!$B416,EmployeeNames)),EmployeeNames)) -> ABAD, FLORIDA RAMOS | OW2: =IF('Loan Due Import'!$B417="",EmployeeNames,_xlfn._xlws.FILTER(EmployeeNames,ISNUMBER(SEARCH('Loan Due Import'!$B417,EmployeeNames)),EmployeeNames)) -> ABAD, FLORIDA RAMOS | OX2: =IF('Loan Due Import'!$B418="",EmployeeNames,_xlfn._xlws.FILTER(EmployeeNames,ISNUMBER(SEARCH('Loan Due Import'!$B418,EmployeeNames)),EmployeeNames)) -> ABAD, FLORIDA RAMOS | OY2: =IF('Loan Due Import'!$B419="",EmployeeNames,_xlfn._xlws.FILTER(EmployeeNames,ISNUMBER(SEARCH('Loan Due Import'!$B419,EmployeeNames)),EmployeeNames)) -> ABAD, FLORIDA RAMOS | OZ2: =IF('Loan Due Import'!$B420="",EmployeeNames,_xlfn._xlws.FILTER(EmployeeNames,ISNUMBER(SEARCH('Loan Due Import'!$B420,EmployeeNames)),EmployeeNames)) -> ABAD, FLORIDA RAMOS | PA2: =IF('Loan Due Import'!$B421="",EmployeeNames,_xlfn._xlws.FILTER(EmployeeNames,ISNUMBER(SEARCH('Loan Due Import'!$B421,EmployeeNames)),EmployeeNames)) -> ABAD, FLORIDA RAMOS | PB2: =IF('Loan Due Import'!$B422="",EmployeeNames,_xlfn._xlws.FILTER(EmployeeNames,ISNUMBER(SEARCH('Loan Due Import'!$B422,EmployeeNames)),EmployeeNames)) -> ABAD, FLORIDA RAMOS | PC2: =IF('Loan Due Import'!$B423="",EmployeeNames,_xlfn._xlws.FILTER(EmployeeNames,ISNUMBER(SEARCH('Loan Due Import'!$B423,EmployeeNames)),EmployeeNames)) -> ABAD, FLORIDA RAMOS | PD2: =IF('Loan Due Import'!$B424="",EmployeeNames,_xlfn._xlws.FILTER(EmployeeNames,ISNUMBER(SEARCH('Loan Due Import'!$B424,EmployeeNames)),EmployeeNames)) -> ABAD, FLORIDA RAMOS | PE2: =IF('Loan Due Import'!$B425="",EmployeeNames,_xlfn._xlws.FILTER(EmployeeNames,ISNUMBER(SEARCH('Loan Due Import'!$B425,EmployeeNames)),EmployeeNames)) -> ABAD, FLORIDA RAMOS | PF2: =IF('Loan Due Import'!$B426="",EmployeeNames,_xlfn._xlws.FILTER(EmployeeNames,ISNUMBER(SEARCH('Loan Due Import'!$B426,EmployeeNames)),EmployeeNames)) -> ABAD, FLORIDA RAMOS | PG2: =IF('Loan Due Import'!$B427="",EmployeeNames,_xlfn._xlws.FILTER(EmployeeNames,ISNUMBER(SEARCH('Loan Due Import'!$B427,EmployeeNames)),EmployeeNames)) -> ABAD, FLORIDA RAMOS | PH2: =IF('Loan Due Import'!$B428="",EmployeeNames,_xlfn._xlws.FILTER(EmployeeNames,ISNUMBER(SEARCH('Loan Due Import'!$B428,EmployeeNames)),EmployeeNames)) -> ABAD, FLORIDA RAMOS | PI2: =IF('Loan Due Import'!$B429="",EmployeeNames,_xlfn._xlws.FILTER(EmployeeNames,ISNUMBER(SEARCH('Loan Due Import'!$B429,EmployeeNames)),EmployeeNames)) -> ABAD, FLORIDA RAMOS | PJ2: =IF('Loan Due Import'!$B430="",EmployeeNames,_xlfn._xlws.FILTER(EmployeeNames,ISNUMBER(SEARCH('Loan Due Import'!$B430,EmployeeNames)),EmployeeNames)) -> ABAD, FLORIDA RAMOS | PK2: =IF('Loan Due Import'!$B431="",EmployeeNames,_xlfn._xlws.FILTER(EmployeeNames,ISNUMBER(SEARCH('Loan Due Import'!$B431,EmployeeNames)),EmployeeNames)) -> ABAD, FLORIDA RAMOS | PL2: =IF('Loan Due Import'!$B432="",EmployeeNames,_xlfn._xlws.FILTER(EmployeeNames,ISNUMBER(SEARCH('Loan Due Import'!$B432,EmployeeNames)),EmployeeNames)) -> ABAD, FLORIDA RAMOS | PM2: =IF('Loan Due Import'!$B433="",EmployeeNames,_xlfn._xlws.FILTER(EmployeeNames,ISNUMBER(SEARCH('Loan Due Import'!$B433,EmployeeNames)),EmployeeNames)) -> ABAD, FLORIDA RAMOS | PN2: =IF('Loan Due Import'!$B434="",EmployeeNames,_xlfn._xlws.FILTER(EmployeeNames,ISNUMBER(SEARCH('Loan Due Import'!$B434,EmployeeNames)),EmployeeNames)) -> ABAD, FLORIDA RAMOS | PO2: =IF('Loan Due Import'!$B435="",EmployeeNames,_xlfn._xlws.FILTER(EmployeeNames,ISNUMBER(SEARCH('Loan Due Import'!$B435,EmployeeNames)),EmployeeNames)) -> ABAD, FLORIDA RAMOS | PP2: =IF('Loan Due Import'!$B436="",EmployeeNames,_xlfn._xlws.FILTER(EmployeeNames,ISNUMBER(SEARCH('Loan Due Import'!$B436,EmployeeNames)),EmployeeNames)) -> ABAD, FLORIDA RAMOS | PQ2: =IF('Loan Due Import'!$B437="",EmployeeNames,_xlfn._xlws.FILTER(EmployeeNames,ISNUMBER(SEARCH('Loan Due Import'!$B437,EmployeeNames)),EmployeeNames)) -> ABAD, FLORIDA RAMOS | PR2: =IF('Loan Due Import'!$B438="",EmployeeNames,_xlfn._xlws.FILTER(EmployeeNames,ISNUMBER(SEARCH('Loan Due Import'!$B438,EmployeeNames)),EmployeeNames)) -> ABAD, FLORIDA RAMOS | PS2: =IF('Loan Due Import'!$B439="",EmployeeNames,_xlfn._xlws.FILTER(EmployeeNames,ISNUMBER(SEARCH('Loan Due Import'!$B439,EmployeeNames)),EmployeeNames)) -> ABAD, FLORIDA RAMOS | PT2: =IF('Loan Due Import'!$B440="",EmployeeNames,_xlfn._xlws.FILTER(EmployeeNames,ISNUMBER(SEARCH('Loan Due Import'!$B440,EmployeeNames)),EmployeeNames)) -> ABAD, FLORIDA RAMOS | PU2: =IF('Loan Due Import'!$B441="",EmployeeNames,_xlfn._xlws.FILTER(EmployeeNames,ISNUMBER(SEARCH('Loan Due Import'!$B441,EmployeeNames)),EmployeeNames)) -> ABAD, FLORIDA RAMOS | PV2: =IF('Loan Due Import'!$B442="",EmployeeNames,_xlfn._xlws.FILTER(EmployeeNames,ISNUMBER(SEARCH('Loan Due Import'!$B442,EmployeeNames)),EmployeeNames)) -> ABAD, FLORIDA RAMOS | PW2: =IF('Loan Due Import'!$B443="",EmployeeNames,_xlfn._xlws.FILTER(EmployeeNames,ISNUMBER(SEARCH('Loan Due Import'!$B443,EmployeeNames)),EmployeeNames)) -> ABAD, FLORIDA RAMOS | PX2: =IF('Loan Due Import'!$B444="",EmployeeNames,_xlfn._xlws.FILTER(EmployeeNames,ISNUMBER(SEARCH('Loan Due Import'!$B444,EmployeeNames)),EmployeeNames)) -> ABAD, FLORIDA RAMOS | PY2: =IF('Loan Due Import'!$B445="",EmployeeNames,_xlfn._xlws.FILTER(EmployeeNames,ISNUMBER(SEARCH('Loan Due Import'!$B445,EmployeeNames)),EmployeeNames)) -> ABAD, FLORIDA RAMOS | PZ2: =IF('Loan Due Import'!$B446="",EmployeeNames,_xlfn._xlws.FILTER(EmployeeNames,ISNUMBER(SEARCH('Loan Due Import'!$B446,EmployeeNames)),EmployeeNames)) -> ABAD, FLORIDA RAMOS | QA2: =IF('Loan Due Import'!$B447="",EmployeeNames,_xlfn._xlws.FILTER(EmployeeNames,ISNUMBER(SEARCH('Loan Due Import'!$B447,EmployeeNames)),EmployeeNames)) -> ABAD, FLORIDA RAMOS | QB2: =IF('Loan Due Import'!$B448="",EmployeeNames,_xlfn._xlws.FILTER(EmployeeNames,ISNUMBER(SEARCH('Loan Due Import'!$B448,EmployeeNames)),EmployeeNames)) -> ABAD, FLORIDA RAMOS | QC2: =IF('Loan Due Import'!$B449="",EmployeeNames,_xlfn._xlws.FILTER(EmployeeNames,ISNUMBER(SEARCH('Loan Due Import'!$B449,EmployeeNames)),EmployeeNames)) -> ABAD, FLORIDA RAMOS | QD2: =IF('Loan Due Import'!$B450="",EmployeeNames,_xlfn._xlws.FILTER(EmployeeNames,ISNUMBER(SEARCH('Loan Due Import'!$B450,EmployeeNames)),EmployeeNames)) -> ABAD, FLORIDA RAMOS | QE2: =IF('Loan Due Import'!$B451="",EmployeeNames,_xlfn._xlws.FILTER(EmployeeNames,ISNUMBER(SEARCH('Loan Due Import'!$B451,EmployeeNames)),EmployeeNames)) -> ABAD, FLORIDA RAMOS | QF2: =IF('Loan Due Import'!$B452="",EmployeeNames,_xlfn._xlws.FILTER(EmployeeNames,ISNUMBER(SEARCH('Loan Due Import'!$B452,EmployeeNames)),EmployeeNames)) -> ABAD, FLORIDA RAMOS | QG2: =IF('Loan Due Import'!$B453="",EmployeeNames,_xlfn._xlws.FILTER(EmployeeNames,ISNUMBER(SEARCH('Loan Due Import'!$B453,EmployeeNames)),EmployeeNames)) -> ABAD, FLORIDA RAMOS | QH2: =IF('Loan Due Import'!$B454="",EmployeeNames,_xlfn._xlws.FILTER(EmployeeNames,ISNUMBER(SEARCH('Loan Due Import'!$B454,EmployeeNames)),EmployeeNames)) -> ABAD, FLORIDA RAMOS | QI2: =IF('Loan Due Import'!$B455="",EmployeeNames,_xlfn._xlws.FILTER(EmployeeNames,ISNUMBER(SEARCH('Loan Due Import'!$B455,EmployeeNames)),EmployeeNames)) -> ABAD, FLORIDA RAMOS | QJ2: =IF('Loan Due Import'!$B456="",EmployeeNames,_xlfn._xlws.FILTER(EmployeeNames,ISNUMBER(SEARCH('Loan Due Import'!$B456,EmployeeNames)),EmployeeNames)) -> ABAD, FLORIDA RAMOS | QK2: =IF('Loan Due Import'!$B457="",EmployeeNames,_xlfn._xlws.FILTER(EmployeeNames,ISNUMBER(SEARCH('Loan Due Import'!$B457,EmployeeNames)),EmployeeNames)) -> ABAD, FLORIDA RAMOS | QL2: =IF('Loan Due Import'!$B458="",EmployeeNames,_xlfn._xlws.FILTER(EmployeeNames,ISNUMBER(SEARCH('Loan Due Import'!$B458,EmployeeNames)),EmployeeNames)) -> ABAD, FLORIDA RAMOS | QM2: =IF('Loan Due Import'!$B459="",EmployeeNames,_xlfn._xlws.FILTER(EmployeeNames,ISNUMBER(SEARCH('Loan Due Import'!$B459,EmployeeNames)),EmployeeNames)) -> ABAD, FLORIDA RAMOS | QN2: =IF('Loan Due Import'!$B460="",EmployeeNames,_xlfn._xlws.FILTER(EmployeeNames,ISNUMBER(SEARCH('Loan Due Import'!$B460,EmployeeNames)),EmployeeNames)) -> ABAD, FLORIDA RAMOS | QO2: =IF('Loan Due Import'!$B461="",EmployeeNames,_xlfn._xlws.FILTER(EmployeeNames,ISNUMBER(SEARCH('Loan Due Import'!$B461,EmployeeNames)),EmployeeNames)) -> ABAD, FLORIDA RAMOS | QP2: =IF('Loan Due Import'!$B462="",EmployeeNames,_xlfn._xlws.FILTER(EmployeeNames,ISNUMBER(SEARCH('Loan Due Import'!$B462,EmployeeNames)),EmployeeNames)) -> ABAD, FLORIDA RAMOS | QQ2: =IF('Loan Due Import'!$B463="",EmployeeNames,_xlfn._xlws.FILTER(EmployeeNames,ISNUMBER(SEARCH('Loan Due Import'!$B463,EmployeeNames)),EmployeeNames)) -> ABAD, FLORIDA RAMOS | QR2: =IF('Loan Due Import'!$B464="",EmployeeNames,_xlfn._xlws.FILTER(EmployeeNames,ISNUMBER(SEARCH('Loan Due Import'!$B464,EmployeeNames)),EmployeeNames)) -> ABAD, FLORIDA RAMOS | QS2: =IF('Loan Due Import'!$B465="",EmployeeNames,_xlfn._xlws.FILTER(EmployeeNames,ISNUMBER(SEARCH('Loan Due Import'!$B465,EmployeeNames)),EmployeeNames)) -> ABAD, FLORIDA RAMOS | QT2: =IF('Loan Due Import'!$B466="",EmployeeNames,_xlfn._xlws.FILTER(EmployeeNames,ISNUMBER(SEARCH('Loan Due Import'!$B466,EmployeeNames)),EmployeeNames)) -> ABAD, FLORIDA RAMOS | QU2: =IF('Loan Due Import'!$B467="",EmployeeNames,_xlfn._xlws.FILTER(EmployeeNames,ISNUMBER(SEARCH('Loan Due Import'!$B467,EmployeeNames)),EmployeeNames)) -> ABAD, FLORIDA RAMOS | QV2: =IF('Loan Due Import'!$B468="",EmployeeNames,_xlfn._xlws.FILTER(EmployeeNames,ISNUMBER(SEARCH('Loan Due Import'!$B468,EmployeeNames)),EmployeeNames)) -> ABAD, FLORIDA RAMOS | QW2: =IF('Loan Due Import'!$B469="",EmployeeNames,_xlfn._xlws.FILTER(EmployeeNames,ISNUMBER(SEARCH('Loan Due Import'!$B469,EmployeeNames)),EmployeeNames)) -> ABAD, FLORIDA RAMOS | QX2: =IF('Loan Due Import'!$B470="",EmployeeNames,_xlfn._xlws.FILTER(EmployeeNames,ISNUMBER(SEARCH('Loan Due Import'!$B470,EmployeeNames)),EmployeeNames)) -> ABAD, FLORIDA RAMOS | QY2: =IF('Loan Due Import'!$B471="",EmployeeNames,_xlfn._xlws.FILTER(EmployeeNames,ISNUMBER(SEARCH('Loan Due Import'!$B471,EmployeeNames)),EmployeeNames)) -> ABAD, FLORIDA RAMOS | QZ2: =IF('Loan Due Import'!$B472="",EmployeeNames,_xlfn._xlws.FILTER(EmployeeNames,ISNUMBER(SEARCH('Loan Due Import'!$B472,EmployeeNames)),EmployeeNames)) -> ABAD, FLORIDA RAMOS | RA2: =IF('Loan Due Import'!$B473="",EmployeeNames,_xlfn._xlws.FILTER(EmployeeNames,ISNUMBER(SEARCH('Loan Due Import'!$B473,EmployeeNames)),EmployeeNames)) -> ABAD, FLORIDA RAMOS | RB2: =IF('Loan Due Import'!$B474="",EmployeeNames,_xlfn._xlws.FILTER(EmployeeNames,ISNUMBER(SEARCH('Loan Due Import'!$B474,EmployeeNames)),EmployeeNames)) -> ABAD, FLORIDA RAMOS | RC2: =IF('Loan Due Import'!$B475="",EmployeeNames,_xlfn._xlws.FILTER(EmployeeNames,ISNUMBER(SEARCH('Loan Due Import'!$B475,EmployeeNames)),EmployeeNames)) -> ABAD, FLORIDA RAMOS | RD2: =IF('Loan Due Import'!$B476="",EmployeeNames,_xlfn._xlws.FILTER(EmployeeNames,ISNUMBER(SEARCH('Loan Due Import'!$B476,EmployeeNames)),EmployeeNames)) -> ABAD, FLORIDA RAMOS | RE2: =IF('Loan Due Import'!$B477="",EmployeeNames,_xlfn._xlws.FILTER(EmployeeNames,ISNUMBER(SEARCH('Loan Due Import'!$B477,EmployeeNames)),EmployeeNames)) -> ABAD, FLORIDA RAMOS | RF2: =IF('Loan Due Import'!$B478="",EmployeeNames,_xlfn._xlws.FILTER(EmployeeNames,ISNUMBER(SEARCH('Loan Due Import'!$B478,EmployeeNames)),EmployeeNames)) -> ABAD, FLORIDA RAMOS | RG2: =IF('Loan Due Import'!$B479="",EmployeeNames,_xlfn._xlws.FILTER(EmployeeNames,ISNUMBER(SEARCH('Loan Due Import'!$B479,EmployeeNames)),EmployeeNames)) -> ABAD, FLORIDA RAMOS | RH2: =IF('Loan Due Import'!$B480="",EmployeeNames,_xlfn._xlws.FILTER(EmployeeNames,ISNUMBER(SEARCH('Loan Due Import'!$B480,EmployeeNames)),EmployeeNames)) -> ABAD, FLORIDA RAMOS | RI2: =IF('Loan Due Import'!$B481="",EmployeeNames,_xlfn._xlws.FILTER(EmployeeNames,ISNUMBER(SEARCH('Loan Due Import'!$B481,EmployeeNames)),EmployeeNames)) -> ABAD, FLORIDA RAMOS | RJ2: =IF('Loan Due Import'!$B482="",EmployeeNames,_xlfn._xlws.FILTER(EmployeeNames,ISNUMBER(SEARCH('Loan Due Import'!$B482,EmployeeNames)),EmployeeNames)) -> ABAD, FLORIDA RAMOS | RK2: =IF('Loan Due Import'!$B483="",EmployeeNames,_xlfn._xlws.FILTER(EmployeeNames,ISNUMBER(SEARCH('Loan Due Import'!$B483,EmployeeNames)),EmployeeNames)) -> ABAD, FLORIDA RAMOS | RL2: =IF('Loan Due Import'!$B484="",EmployeeNames,_xlfn._xlws.FILTER(EmployeeNames,ISNUMBER(SEARCH('Loan Due Import'!$B484,EmployeeNames)),EmployeeNames)) -> ABAD, FLORIDA RAMOS | RM2: =IF('Loan Due Import'!$B485="",EmployeeNames,_xlfn._xlws.FILTER(EmployeeNames,ISNUMBER(SEARCH('Loan Due Import'!$B485,EmployeeNames)),EmployeeNames)) -> ABAD, FLORIDA RAMOS | RN2: =IF('Loan Due Import'!$B486="",EmployeeNames,_xlfn._xlws.FILTER(EmployeeNames,ISNUMBER(SEARCH('Loan Due Import'!$B486,EmployeeNames)),EmployeeNames)) -> ABAD, FLORIDA RAMOS | RO2: =IF('Loan Due Import'!$B487="",EmployeeNames,_xlfn._xlws.FILTER(EmployeeNames,ISNUMBER(SEARCH('Loan Due Import'!$B487,EmployeeNames)),EmployeeNames)) -> ABAD, FLORIDA RAMOS | RP2: =IF('Loan Due Import'!$B488="",EmployeeNames,_xlfn._xlws.FILTER(EmployeeNames,ISNUMBER(SEARCH('Loan Due Import'!$B488,EmployeeNames)),EmployeeNames)) -> ABAD, FLORIDA RAMOS | RQ2: =IF('Loan Due Import'!$B489="",EmployeeNames,_xlfn._xlws.FILTER(EmployeeNames,ISNUMBER(SEARCH('Loan Due Import'!$B489,EmployeeNames)),EmployeeNames)) -> ABAD, FLORIDA RAMOS | RR2: =IF('Loan Due Import'!$B490="",EmployeeNames,_xlfn._xlws.FILTER(EmployeeNames,ISNUMBER(SEARCH('Loan Due Import'!$B490,EmployeeNames)),EmployeeNames)) -> ABAD, FLORIDA RAMOS | RS2: =IF('Loan Due Import'!$B491="",EmployeeNames,_xlfn._xlws.FILTER(EmployeeNames,ISNUMBER(SEARCH('Loan Due Import'!$B491,EmployeeNames)),EmployeeNames)) -> ABAD, FLORIDA RAMOS | RT2: =IF('Loan Due Import'!$B492="",EmployeeNames,_xlfn._xlws.FILTER(EmployeeNames,ISNUMBER(SEARCH('Loan Due Import'!$B492,EmployeeNames)),EmployeeNames)) -> ABAD, FLORIDA RAMOS | RU2: =IF('Loan Due Import'!$B493="",EmployeeNames,_xlfn._xlws.FILTER(EmployeeNames,ISNUMBER(SEARCH('Loan Due Import'!$B493,EmployeeNames)),EmployeeNames)) -> ABAD, FLORIDA RAMOS | RV2: =IF('Loan Due Import'!$B494="",EmployeeNames,_xlfn._xlws.FILTER(EmployeeNames,ISNUMBER(SEARCH('Loan Due Import'!$B494,EmployeeNames)),EmployeeNames)) -> ABAD, FLORIDA RAMOS | RW2: =IF('Loan Due Import'!$B495="",EmployeeNames,_xlfn._xlws.FILTER(EmployeeNames,ISNUMBER(SEARCH('Loan Due Import'!$B495,EmployeeNames)),EmployeeNames)) -> ABAD, FLORIDA RAMOS | RX2: =IF('Loan Due Import'!$B496="",EmployeeNames,_xlfn._xlws.FILTER(EmployeeNames,ISNUMBER(SEARCH('Loan Due Import'!$B496,EmployeeNames)),EmployeeNames)) -> ABAD, FLORIDA RAMOS | RY2: =IF('Loan Due Import'!$B497="",EmployeeNames,_xlfn._xlws.FILTER(EmployeeNames,ISNUMBER(SEARCH('Loan Due Import'!$B497,EmployeeNames)),EmployeeNames)) -> ABAD, FLORIDA RAMOS | RZ2: =IF('Loan Due Import'!$B498="",EmployeeNames,_xlfn._xlws.FILTER(EmployeeNames,ISNUMBER(SEARCH('Loan Due Import'!$B498,EmployeeNames)),EmployeeNames)) -> ABAD, FLORIDA RAMOS | SA2: =IF('Loan Due Import'!$B499="",EmployeeNames,_xlfn._xlws.FILTER(EmployeeNames,ISNUMBER(SEARCH('Loan Due Import'!$B499,EmployeeNames)),EmployeeNames)) -> ABAD, FLORIDA RAMOS | SB2: =IF('Loan Due Import'!$B500="",EmployeeNames,_xlfn._xlws.FILTER(EmployeeNames,ISNUMBER(SEARCH('Loan Due Import'!$B500,EmployeeNames)),EmployeeNames)) -> ABAD, FLORIDA RAMOS | SC2: =IF('Loan Due Import'!$B501="",EmployeeNames,_xlfn._xlws.FILTER(EmployeeNames,ISNUMBER(SEARCH('Loan Due Import'!$B501,EmployeeNames)),EmployeeNames)) -> ABAD, FLORIDA RAMOS | SD2: =IF('Loan Due Import'!$B502="",EmployeeNames,_xlfn._xlws.FILTER(EmployeeNames,ISNUMBER(SEARCH('Loan Due Import'!$B502,EmployeeNames)),EmployeeNames)) -> ABAD, FLORIDA RAMOS | SE2: =IF('Loan Due Import'!$B503="",EmployeeNames,_xlfn._xlws.FILTER(EmployeeNames,ISNUMBER(SEARCH('Loan Due Import'!$B503,EmployeeNames)),EmployeeNames)) -> ABAD, FLORIDA RAMOS | SF2: =IF('Loan Due Import'!$B504="",EmployeeNames,_xlfn._xlws.FILTER(EmployeeNames,ISNUMBER(SEARCH('Loan Due Import'!$B504,EmployeeNames)),EmployeeNames)) -> ABAD, FLORIDA RAMOS

Sheet Instructions
A1: Field | B1: Required | C1: Notes
A2: Entity | B2: Yes | C2: Choose once in cell B1. All rows in the workbook use this entity.
A3: Due Month | B3: Yes | C3: Use the first day of the payroll month, for example 2026-05-01.
A4: Employee Search | B4: No | C4: Type the beginning of the lastname to narrow the employee dropdown on the same row.
A5: Employee ID | B5: Auto | C5: Auto-fills from the selected employee name. Keep the formula intact.
A6: Employee Name | B6: Yes | C6: Select from the searchable dropdown sourced from the locked Employee Records sheet.
A7: Loan/Account No. | B7: Yes | C7: PN number, contract reference, application number, or account reference.
A8: Monthly Amortization | B8: Yes | C8: Scheduled monthly amortization from the source billing.
A9: Amount Due | B9: Yes | C9: Deduction amount for the selected payroll month.
A10: Outstanding/Principal/Interest/Penalty | B10: No | C10: Optional audit fields retained from bank/entity files.
